{"skeleton":{"hash":"Klmp46fyDHZN4vT3OiKLGMuHUME","spine":"3.8.72","x":-46.16,"y":-25.68,"width":96.51,"height":69.28,"images":"./images/","audio":"D:/Huydrive9633/2. BraveStars/2. SR4/Anim/LadyBug"},"bones":[{"name":"root"},{"name":"bone2","parent":"root","y":-69.92},{"name":"bone","parent":"bone2","x":8.22,"y":72.18},{"name":"body","parent":"bone","length":15.13,"rotation":34.81,"x":1.02,"y":0.34},{"name":"head","parent":"bone","length":14.79,"rotation":-127.69,"x":-25.83,"y":9.95},{"name":"eyes","parent":"head","x":12.11,"y":-1.94},{"name":"R-cang","parent":"head","length":11.93,"rotation":33.09,"x":10.18,"y":12.99},{"name":"L-cang","parent":"head","length":11.78,"rotation":-16.12,"x":17.14,"y":-5.24},{"name":"fx","parent":"bone2"},{"name":"Layer 6","parent":"body","length":15.95,"rotation":79.63,"x":19.24,"y":15.74},{"name":"Layer 8","parent":"body","length":20.62,"rotation":-10.04,"x":23.71,"y":9.13},{"name":"Layer 7","parent":"body","length":19.69,"rotation":-33.41,"x":25.45,"y":1.34}],"slots":[{"name":"Layer 6","bone":"Layer 6","dark":"000000","attachment":"Layer 6"},{"name":"Layer 7","bone":"Layer 7","dark":"000000","attachment":"Layer 7"},{"name":"Layer 8","bone":"Layer 8","dark":"000000","attachment":"Layer 8"},{"name":"body","bone":"body","dark":"000000","attachment":"body"},{"name":"Layer 5","bone":"body","dark":"000000","attachment":"Layer 5"},{"name":"R-cang","bone":"R-cang","dark":"000000","attachment":"R-cang"},{"name":"L-cang","bone":"L-cang","dark":"000000","attachment":"L-cang"},{"name":"head","bone":"head","dark":"000000","attachment":"head"},{"name":"eyes","bone":"eyes","dark":"000000","attachment":"eyes"},{"name":"fx","bone":"fx","dark":"000000"}],"skins":[{"name":"default","attachments":{"Layer 5":{"Layer 5":{"x":-11.17,"y":12.56,"rotation":-49.71,"width":32,"height":35}},"Layer 6":{"Layer 6":{"x":7.56,"y":-1.72,"rotation":-114.44,"width":14,"height":19}},"Layer 7":{"Layer 7":{"x":8.97,"y":-0.28,"rotation":-1.4,"width":24,"height":10}},"Layer 8":{"Layer 8":{"x":9.4,"y":-0.19,"rotation":-24.78,"width":23,"height":15}},"fx":{"fx/fx0 (00)":{"width":126,"height":126},"fx/fx0 (01)":{"width":126,"height":126},"fx/fx0 (02)":{"width":126,"height":126},"fx/fx0 (03)":{"width":126,"height":126},"fx/fx0 (04)":{"width":126,"height":126},"fx/fx0 (05)":{"width":126,"height":126},"fx/fx0 (06)":{"width":126,"height":126},"fx/fx0 (07)":{"width":126,"height":126},"fx/fx0 (08)":{"width":126,"height":126},"fx/fx0 (09)":{"width":126,"height":126}},"head":{"head":{"x":2.48,"y":-0.04,"rotation":127.69,"width":34,"height":41}},"body":{"body":{"x":-0.11,"y":-0.26,"rotation":-34.81,"width":57,"height":56}},"eyes":{"eyes":{"x":-4,"y":3.47,"rotation":127.69,"width":31,"height":21},"eyes_atk":{"x":-4,"y":3.47,"rotation":127.69,"width":38,"height":22},"eyes_fire":{"x":-4,"y":3.47,"rotation":127.69,"width":33,"height":21},"get-hit":{"x":-4,"y":3.47,"rotation":121.29,"width":39,"height":23}},"R-cang":{"R-cang":{"x":7.03,"y":-4.25,"rotation":119.99,"width":22,"height":20}},"L-cang":{"L-cang":{"x":8.96,"y":2.23,"rotation":143.82,"width":16,"height":24}}}}],"events":{"AddForceForward":{},"Aim":{},"Fire":{},"FixedAim":{},"SkillComplete":{}},"animations":{"Atk":{"bones":{"bone":{"translate":[{"y":-9.33,"curve":0.25,"c3":0.313},{"time":0.5,"x":19.88,"y":10.55,"curve":0.25,"c3":0.402},{"time":0.5667,"x":-18.74,"y":-18.18,"curve":0.782,"c3":0.75},{"time":1.1667,"y":-9.33}]},"L-cang":{"rotate":[{"curve":0.25,"c3":0.313},{"time":0.5667,"angle":51.35,"curve":0,"c2":0.71,"c3":0.252},{"time":0.6,"angle":-42.77,"curve":0.25,"c3":0.75},{"time":1.1667}]},"R-cang":{"rotate":[{"curve":0.25,"c3":0.313},{"time":0.5667,"angle":-43.06,"curve":0,"c2":0.71,"c3":0.252},{"time":0.6,"angle":30.68,"curve":0.25,"c3":0.75},{"time":1.1667}]},"eyes":{"scale":[{"curve":0.25,"c3":0.313},{"time":0.5,"x":1.001,"y":1.001,"curve":0.25,"c3":0.75},{"time":0.6,"y":0.879,"curve":"stepped"},{"time":0.8333,"y":0.879,"curve":0.25,"c3":0.75},{"time":0.9667}],"shear":[{"curve":0.25,"c3":0.313},{"time":0.5,"x":-16.14,"curve":0.25,"c3":0.75},{"time":0.6}]},"head":{"translate":[{"x":0.08,"y":-0.45,"curve":0.375,"c2":0.5,"c3":0.75},{"time":0.5,"x":-0.39,"y":10.54,"curve":0.25,"c3":0.805,"c4":0.31},{"time":0.5667,"x":-3.9,"y":-17.01,"curve":0.25,"c3":0.272},{"time":0.8,"x":-5.11,"y":-18.58,"curve":0.564,"c3":0.866,"c4":0.62},{"time":1.1667,"x":0.08,"y":-0.45}],"shear":[{"time":0.5,"curve":"stepped"},{"time":0.5333,"x":-18.9,"curve":"stepped"},{"time":0.5667}]},"body":{"scale":[{"curve":0.25,"c3":0.313},{"time":0.5,"x":1.141,"y":1.141,"curve":0.25,"c3":0.429},{"time":0.6,"x":1.291,"y":0.804,"curve":0.912,"c3":0.75},{"time":1.1667}]},"Layer 7":{"rotate":[{"angle":56.88,"curve":0.25,"c3":0.75},{"time":0.1,"angle":-37.89,"curve":0.25,"c3":0.75},{"time":0.2,"angle":56.88,"curve":0.25,"c3":0.75},{"time":0.3,"angle":-37.89,"curve":0.25,"c3":0.75},{"time":0.4,"angle":56.88,"curve":0.25,"c3":0.75},{"time":0.5,"angle":-37.89,"curve":0.25,"c3":0.75},{"time":0.5667,"angle":56.15},{"time":0.5677,"angle":56.88,"curve":"stepped"},{"time":0.8333,"angle":56.88,"curve":0.25,"c3":0.75},{"time":0.9333,"angle":-37.89,"curve":0.25,"c3":0.75},{"time":1.0333,"angle":56.88,"curve":0.25,"c3":0.75},{"time":1.1667,"angle":-37.89}]},"Layer 8":{"rotate":[{"angle":-9.19,"curve":0.382,"c2":0.57,"c3":0.735},{"time":0.0333,"angle":-27.96,"curve":0.25,"c3":0.75},{"time":0.1333,"angle":38.17,"curve":0.25,"c3":0.75},{"time":0.2333,"angle":-27.96,"curve":0.25,"c3":0.75},{"time":0.3333,"angle":38.17,"curve":0.25,"c3":0.75},{"time":0.4333,"angle":-27.96,"curve":0.25,"c3":0.75},{"time":0.5333,"angle":38.17,"curve":"stepped"},{"time":0.8333,"angle":38.17},{"time":0.8667,"angle":-27.96,"curve":0.25,"c3":0.75},{"time":0.9667,"angle":38.17,"curve":0.25,"c3":0.75},{"time":1.0667,"angle":-27.96,"curve":0.25,"c3":0.75},{"time":1.1667,"angle":38.17}]},"Layer 6":{"rotate":[{"angle":11.01,"curve":0.382,"c2":0.57,"c3":0.735},{"time":0.0333,"angle":34.82,"curve":0.25,"c3":0.75},{"time":0.1333,"angle":-49.09,"curve":0.25,"c3":0.75},{"time":0.2333,"angle":34.82,"curve":0.25,"c3":0.75},{"time":0.3333,"angle":-49.09,"curve":0.25,"c3":0.75},{"time":0.4333,"angle":34.82,"curve":0.25,"c3":0.75},{"time":0.5333,"angle":-49.09,"curve":"stepped"},{"time":0.8333,"angle":-49.09},{"time":0.8667,"angle":34.82,"curve":0.25,"c3":0.75},{"time":0.9667,"angle":-49.09,"curve":0.25,"c3":0.75},{"time":1.0667,"angle":34.82,"curve":0.25,"c3":0.75},{"time":1.1667,"angle":-49.09}]}},"events":[{"time":0.0667,"name":"Aim"},{"time":0.5667,"name":"Fire"},{"time":1.0667,"name":"SkillComplete"}]},"Atk2":{"bones":{"bone":{"translate":[{"y":-9.33,"curve":0.25,"c3":0.313},{"time":0.5,"x":19.88,"y":10.55,"curve":0.25,"c3":0.402},{"time":0.5667,"x":-18.74,"y":-18.18,"curve":0.782,"c3":0.75},{"time":1.1667,"y":-9.33}]},"L-cang":{"rotate":[{"curve":0.25,"c3":0.313},{"time":0.5667,"angle":51.35,"curve":0,"c2":0.71,"c3":0.252},{"time":0.6,"angle":-42.77,"curve":0.25,"c3":0.75},{"time":1.1667}]},"R-cang":{"rotate":[{"curve":0.25,"c3":0.313},{"time":0.5667,"angle":-43.06,"curve":0,"c2":0.71,"c3":0.252},{"time":0.6,"angle":30.68,"curve":0.25,"c3":0.75},{"time":1.1667}]},"eyes":{"scale":[{"curve":0.25,"c3":0.313},{"time":0.5,"x":1.001,"y":1.001,"curve":0.25,"c3":0.75},{"time":0.6,"y":0.879,"curve":"stepped"},{"time":0.8333,"y":0.879,"curve":0.25,"c3":0.75},{"time":0.9667}],"shear":[{"curve":0.25,"c3":0.313},{"time":0.5,"x":-16.14,"curve":0.25,"c3":0.75},{"time":0.6}]},"head":{"translate":[{"x":0.08,"y":-0.45,"curve":0.375,"c2":0.5,"c3":0.75},{"time":0.5,"x":-0.39,"y":10.54,"curve":0.25,"c3":0.805,"c4":0.31},{"time":0.5667,"x":-3.9,"y":-17.01,"curve":0.25,"c3":0.272},{"time":0.8,"x":-5.11,"y":-18.58,"curve":0.564,"c3":0.866,"c4":0.62},{"time":1.1667,"x":0.08,"y":-0.45}],"shear":[{"time":0.5,"curve":"stepped"},{"time":0.5333,"x":-18.9,"curve":"stepped"},{"time":0.5667}]},"body":{"scale":[{"curve":0.25,"c3":0.313},{"time":0.5,"x":1.141,"y":1.141,"curve":0.25,"c3":0.429},{"time":0.6,"x":1.291,"y":0.804,"curve":0.912,"c3":0.75},{"time":1.1667}]},"Layer 7":{"rotate":[{"angle":56.88,"curve":0.25,"c3":0.75},{"time":0.1,"angle":-37.89,"curve":0.25,"c3":0.75},{"time":0.2,"angle":56.88,"curve":0.25,"c3":0.75},{"time":0.3,"angle":-37.89,"curve":0.25,"c3":0.75},{"time":0.4,"angle":56.88,"curve":0.25,"c3":0.75},{"time":0.5,"angle":-37.89,"curve":0.25,"c3":0.75},{"time":0.5667,"angle":56.15},{"time":0.5677,"angle":56.88,"curve":"stepped"},{"time":0.8333,"angle":56.88,"curve":0.25,"c3":0.75},{"time":0.9333,"angle":-37.89,"curve":0.25,"c3":0.75},{"time":1.0333,"angle":56.88,"curve":0.25,"c3":0.75},{"time":1.1667,"angle":-37.89}]},"Layer 8":{"rotate":[{"angle":-9.19,"curve":0.382,"c2":0.57,"c3":0.735},{"time":0.0333,"angle":-27.96,"curve":0.25,"c3":0.75},{"time":0.1333,"angle":38.17,"curve":0.25,"c3":0.75},{"time":0.2333,"angle":-27.96,"curve":0.25,"c3":0.75},{"time":0.3333,"angle":38.17,"curve":0.25,"c3":0.75},{"time":0.4333,"angle":-27.96,"curve":0.25,"c3":0.75},{"time":0.5333,"angle":38.17,"curve":"stepped"},{"time":0.8333,"angle":38.17},{"time":0.8667,"angle":-27.96,"curve":0.25,"c3":0.75},{"time":0.9667,"angle":38.17,"curve":0.25,"c3":0.75},{"time":1.0667,"angle":-27.96,"curve":0.25,"c3":0.75},{"time":1.1667,"angle":38.17}]},"Layer 6":{"rotate":[{"angle":11.01,"curve":0.382,"c2":0.57,"c3":0.735},{"time":0.0333,"angle":34.82,"curve":0.25,"c3":0.75},{"time":0.1333,"angle":-49.09,"curve":0.25,"c3":0.75},{"time":0.2333,"angle":34.82,"curve":0.25,"c3":0.75},{"time":0.3333,"angle":-49.09,"curve":0.25,"c3":0.75},{"time":0.4333,"angle":34.82,"curve":0.25,"c3":0.75},{"time":0.5333,"angle":-49.09,"curve":"stepped"},{"time":0.8333,"angle":-49.09},{"time":0.8667,"angle":34.82,"curve":0.25,"c3":0.75},{"time":0.9667,"angle":-49.09,"curve":0.25,"c3":0.75},{"time":1.0667,"angle":34.82,"curve":0.25,"c3":0.75},{"time":1.1667,"angle":-49.09}]}},"events":[{"time":0.0667,"name":"FixedAim"},{"time":0.5667,"name":"Fire"},{"time":1.0667,"name":"SkillComplete"}]},"Behit":{"slots":{"Layer 6":{"twoColor":[{"light":"ffffffff","dark":"8a8a8a","curve":"stepped"},{"time":0.1,"light":"ffffffff","dark":"8a8a8a"},{"time":0.1667,"light":"ffffffff","dark":"000000"}]},"L-cang":{"twoColor":[{"light":"ffffffff","dark":"8a8a8a","curve":"stepped"},{"time":0.1,"light":"ffffffff","dark":"8a8a8a"},{"time":0.1667,"light":"ffffffff","dark":"000000"}]},"body":{"twoColor":[{"light":"ffffffff","dark":"8a8a8a","curve":"stepped"},{"time":0.1,"light":"ffffffff","dark":"8a8a8a"},{"time":0.1667,"light":"ffffffff","dark":"000000"}]},"eyes":{"twoColor":[{"light":"ffffffff","dark":"8a8a8a","curve":"stepped"},{"time":0.1,"light":"ffffffff","dark":"8a8a8a"},{"time":0.1667,"light":"ffffffff","dark":"000000"}]},"Layer 8":{"twoColor":[{"light":"ffffffff","dark":"8a8a8a","curve":"stepped"},{"time":0.1,"light":"ffffffff","dark":"8a8a8a"},{"time":0.1667,"light":"ffffffff","dark":"000000"}]},"Layer 7":{"twoColor":[{"light":"ffffffff","dark":"8a8a8a","curve":"stepped"},{"time":0.1,"light":"ffffffff","dark":"8a8a8a"},{"time":0.1667,"light":"ffffffff","dark":"000000"}]},"Layer 5":{"twoColor":[{"light":"ffffffff","dark":"8a8a8a","curve":"stepped"},{"time":0.1,"light":"ffffffff","dark":"8a8a8a"},{"time":0.1667,"light":"ffffffff","dark":"000000"}]},"R-cang":{"twoColor":[{"light":"ffffffff","dark":"8a8a8a","curve":"stepped"},{"time":0.1,"light":"ffffffff","dark":"8a8a8a"},{"time":0.1667,"light":"ffffffff","dark":"000000"}]},"head":{"twoColor":[{"light":"ffffffff","dark":"8a8a8a","curve":"stepped"},{"time":0.1,"light":"ffffffff","dark":"8a8a8a"},{"time":0.1667,"light":"ffffffff","dark":"000000"}]}}},"Die-middle":{"slots":{"Layer 6":{"attachment":[{"name":null}]},"body":{"attachment":[{"name":null}]},"eyes":{"attachment":[{"name":"get-hit"}]},"Layer 8":{"attachment":[{"name":null}]},"Layer 7":{"attachment":[{"name":null}]},"Layer 5":{"attachment":[{"name":null}]}},"bones":{"head":{"rotate":[{"angle":-66.82}],"translate":[{"y":-5.26}]},"fx":{"translate":[{"x":-15.3,"y":69.92}]}}},"Die-start":{"slots":{"Layer 6":{"attachment":[{"time":0.1667,"name":null}]},"body":{"twoColor":[{"time":0.1667,"light":"ffffffff","dark":"000000","curve":0.25,"c3":0.75},{"time":0.2333,"light":"ffffff00","dark":"000000"}]},"eyes":{"attachment":[{"time":0.1667,"name":"get-hit"}]},"Layer 8":{"attachment":[{"time":0.1667,"name":null}]},"Layer 7":{"attachment":[{"time":0.1667,"name":null}]},"Layer 5":{"attachment":[{"time":0.1667,"name":null}]},"fx":{"twoColor":[{"light":"54ff00ff","dark":"91ff00","curve":0.25,"c3":0.142,"c4":0.99},{"time":0.1667,"light":"ff0090ff","dark":"ff87d6"}],"attachment":[{"time":0.1667,"name":"fx/fx0 (00)"},{"time":0.2333,"name":"fx/fx0 (02)"},{"time":0.3,"name":"fx/fx0 (04)"},{"time":0.3667,"name":"fx/fx0 (06)"},{"time":0.4333,"name":"fx/fx0 (08)"},{"time":0.5,"name":null}]}},"bones":{"bone":{"scale":[{"curve":0.25,"c3":0.142,"c4":0.99},{"time":0.0667,"x":1.118,"y":1.118}]},"eyes":{"scale":[{"curve":0.25,"c3":0.142,"c4":0.99},{"time":0.1667,"x":1.39,"y":1.39,"curve":0.25,"c3":0.75},{"time":0.3}]},"head":{"rotate":[{"time":0.2333,"curve":0.754,"c2":0.01,"c3":0.833,"c4":0.75},{"time":0.5667,"angle":-66.82}],"translate":[{"x":0.08,"y":-0.45,"curve":0.25,"c3":0.142,"c4":0.99},{"time":0.2333,"curve":0.141,"c2":0.7,"c3":0.233},{"time":0.4333,"y":112.51,"curve":0.624,"c3":0.86,"c4":0.22},{"time":0.5667,"y":89.52,"curve":0.25,"c3":0.75},{"time":0.7,"y":-5.26}]},"body":{"scale":[{"curve":0.25,"c3":0.142,"c4":0.99},{"time":0.1667,"x":1.301,"y":1.301,"curve":0.25,"c3":0.75},{"time":0.5667}]},"fx":{"translate":[{"x":6.93,"y":71.28,"curve":0.25,"c3":0.142,"c4":0.99},{"time":0.1667,"x":29.93,"y":64.48}],"scale":[{"curve":0.25,"c3":0.142,"c4":0.99},{"time":0.1667,"x":2.207,"y":2.207,"curve":0.25,"c3":0.75},{"time":0.5667,"x":2.456,"y":2.456}]}},"events":[{"time":0.0667,"name":"AddForceForward"}]},"Die_end":{"slots":{"Layer 6":{"attachment":[{"name":null}]},"L-cang":{"twoColor":[{"time":0.2667,"light":"ffffffff","dark":"000000","curve":0.25,"c3":0.149},{"time":0.4333,"light":"ffffff00","dark":"000000"}]},"body":{"attachment":[{"name":null}]},"eyes":{"twoColor":[{"time":0.2667,"light":"ffffffff","dark":"000000","curve":0.25,"c3":0.149},{"time":0.4333,"light":"ffffff00","dark":"000000"}],"attachment":[{"name":null}]},"Layer 5":{"attachment":[{"name":null}]},"Layer 8":{"attachment":[{"name":null}]},"Layer 7":{"attachment":[{"name":null}]},"R-cang":{"twoColor":[{"time":0.2667,"light":"ffffffff","dark":"000000","curve":0.25,"c3":0.149},{"time":0.4333,"light":"ffffff00","dark":"000000"}]},"fx":{"attachment":[{"time":0.6,"name":null}]},"head":{"twoColor":[{"time":0.2667,"light":"ffffffff","dark":"000000","curve":0.25,"c3":0.149},{"time":0.4333,"light":"ffffff00","dark":"000000"}]}},"bones":{"head":{"rotate":[{"angle":-66.82}],"translate":[{"y":-5.26}]}}},"Idle":{"bones":{"bone":{"translate":[{"y":-9.33,"curve":0.25,"c3":0.75},{"time":0.6,"curve":0.25,"c3":0.75},{"time":1.2,"y":-9.33}]},"L-cang":{"rotate":[{"time":0.6667,"curve":0.25,"c3":0.75},{"time":0.7333,"angle":51.35,"curve":0.25,"c3":0.75},{"time":0.8,"curve":0.25,"c3":0.75},{"time":0.8667,"angle":51.35,"curve":0.25,"c3":0.75},{"time":0.9333,"curve":0.25,"c3":0.75},{"time":1,"angle":51.35,"curve":0.25,"c3":0.75},{"time":1.0667,"curve":0.25,"c3":0.75},{"time":1.1333,"angle":51.35,"curve":0.25,"c3":0.75},{"time":1.2}]},"R-cang":{"rotate":[{"time":0.6667,"curve":0.25,"c3":0.75},{"time":0.7333,"angle":-43.06,"curve":0.25,"c3":0.75},{"time":0.8,"curve":0.25,"c3":0.75},{"time":0.8667,"angle":-43.06,"curve":0.25,"c3":0.75},{"time":0.9333,"curve":0.25,"c3":0.75},{"time":1,"angle":-43.06,"curve":0.25,"c3":0.75},{"time":1.0667,"curve":0.25,"c3":0.75},{"time":1.1333,"angle":-43.06,"curve":0.25,"c3":0.75},{"time":1.2}]},"head":{"rotate":[{"curve":0.25,"c3":0.75},{"time":0.6,"angle":16.09,"curve":0.25,"c3":0.75},{"time":1.2}],"translate":[{"x":0.08,"y":-0.45,"curve":0.375,"c2":0.5,"c3":0.75},{"time":0.3,"x":0.45,"y":-2.53,"curve":0.25,"c3":0.75},{"time":0.9,"curve":0.25,"c3":0.625,"c4":0.5},{"time":1.2,"x":0.08,"y":-0.45}]},"Layer 7":{"rotate":[{"angle":56.88,"curve":0.25,"c3":0.75},{"time":0.1,"angle":-37.89,"curve":0.25,"c3":0.75},{"time":0.2,"angle":56.88,"curve":0.25,"c3":0.75},{"time":0.3,"angle":-37.89,"curve":0.25,"c3":0.75},{"time":0.4,"angle":56.88,"curve":0.25,"c3":0.75},{"time":0.5,"angle":-37.89,"curve":0.25,"c3":0.75},{"time":0.6,"angle":56.88,"curve":0.25,"c3":0.75},{"time":0.7,"angle":-37.89,"curve":0.25,"c3":0.75},{"time":0.8,"angle":56.88,"curve":0.25,"c3":0.75},{"time":0.9,"angle":-37.89,"curve":0.25,"c3":0.75},{"time":1,"angle":56.88,"curve":0.25,"c3":0.75},{"time":1.1,"angle":-37.89,"curve":0.25,"c3":0.75},{"time":1.2,"angle":56.88}]},"Layer 8":{"rotate":[{"angle":-9.19,"curve":0.382,"c2":0.57,"c3":0.735},{"time":0.0333,"angle":-27.96,"curve":0.25,"c3":0.75},{"time":0.1333,"angle":38.17,"curve":0.25,"c3":0.75},{"time":0.2333,"angle":-27.96,"curve":0.25,"c3":0.75},{"time":0.3333,"angle":38.17,"curve":0.25,"c3":0.75},{"time":0.4333,"angle":-27.96,"curve":0.25,"c3":0.75},{"time":0.5333,"angle":38.17,"curve":0.25,"c3":0.75},{"time":0.6333,"angle":-27.96,"curve":0.25,"c3":0.75},{"time":0.7333,"angle":38.17,"curve":0.25,"c3":0.75},{"time":0.8333,"angle":-27.96,"curve":0.25,"c3":0.75},{"time":0.9333,"angle":38.17,"curve":0.25,"c3":0.75},{"time":1.0333,"angle":-27.96,"curve":0.25,"c3":0.75},{"time":1.1333,"angle":38.17,"curve":0.243,"c3":0.649,"c4":0.6},{"time":1.2,"angle":-9.19}]},"Layer 6":{"rotate":[{"angle":11.01,"curve":0.382,"c2":0.57,"c3":0.735},{"time":0.0333,"angle":34.82,"curve":0.25,"c3":0.75},{"time":0.1333,"angle":-49.09,"curve":0.25,"c3":0.75},{"time":0.2333,"angle":34.82,"curve":0.25,"c3":0.75},{"time":0.3333,"angle":-49.09,"curve":0.25,"c3":0.75},{"time":0.4333,"angle":34.82,"curve":0.25,"c3":0.75},{"time":0.5333,"angle":-49.09,"curve":0.25,"c3":0.75},{"time":0.6333,"angle":34.82,"curve":0.25,"c3":0.75},{"time":0.7333,"angle":-49.09,"curve":0.25,"c3":0.75},{"time":0.8333,"angle":34.82,"curve":0.25,"c3":0.75},{"time":0.9333,"angle":-49.09,"curve":0.25,"c3":0.75},{"time":1.0333,"angle":34.82,"curve":0.25,"c3":0.75},{"time":1.1333,"angle":-49.09,"curve":0.243,"c3":0.649,"c4":0.6},{"time":1.2,"angle":11.01}]}}}}}