{"skeleton":{"hash":"q+wgoijy/DTivRXWINH22L2nNMo","spine":"3.8.72","x":-366.77,"y":-1.45,"width":644.28,"height":512,"images":"./images/","audio":"E:/work/Stick4/Art/Animation/backup/remake/butcher"},"bones":[{"name":"root"},{"name":"move_body","parent":"root","x":0.51,"y":88.24,"color":"f70000ff"},{"name":"body3","parent":"move_body","length":122.49,"rotation":87.75,"x":-0.8,"y":56,"color":"ffcf00ff"},{"name":"body4","parent":"body3","length":143.47,"rotation":5.76,"x":122.49,"color":"ffcf00ff"},{"name":"head","parent":"body4","length":105.78,"rotation":41.18,"x":133.63,"y":9.42,"color":"ff0000ff"},{"name":"eye","parent":"head","rotation":-41.27,"x":70.4,"y":31.67,"color":"ff0000ff"},{"name":"dot","parent":"eye","rotation":41.27,"x":-3.02,"y":4.11,"transform":"noScaleOrReflection"},{"name":"L_arm","parent":"body4","length":151.77,"rotation":-140.5,"x":126.62,"y":-78.32,"color":"ac5858ff"},{"name":"L_forearm","parent":"L_arm","length":73.39,"rotation":-28.55,"x":151.37,"y":-0.38,"transform":"noScale","color":"ac5858ff"},{"name":"L_hand","parent":"L_forearm","length":64.3,"rotation":-7.32,"x":72.79,"y":-0.36,"color":"ac5858ff"},{"name":"weapon","parent":"L_hand","length":150.53,"rotation":-66.23,"x":40.53,"y":-2.49,"color":"5d00fdff"},{"name":"R_arm","parent":"body4","length":151.82,"rotation":160.93,"x":113.82,"y":34.96,"color":"bbff99ff"},{"name":"R_forearm","parent":"R_arm","length":79.01,"rotation":-28.98,"x":151.07,"y":-0.02,"transform":"noScale","color":"bbff99ff"},{"name":"R_hand","parent":"R_forearm","length":56.67,"rotation":10.2,"x":77.95,"y":0.3,"color":"bbff99ff"},{"name":"weapon2","parent":"R_hand","length":150.98,"rotation":-80.99,"x":34.06,"y":-13.53,"color":"00ff8bff"},{"name":"skirt","parent":"body3","length":115.64,"rotation":149.54,"x":60.48,"y":89.91,"color":"007effff"},{"name":"skirt2","parent":"body3","length":109.13,"rotation":-155.67,"x":68.12,"y":-105.04,"color":"007effff"},{"name":"body5","parent":"body3","length":104.98,"rotation":-179.32,"x":48.22,"y":0.64,"color":"007effff"},{"name":"body6","parent":"body3","length":86.5,"rotation":137.58,"x":38.98,"y":53.88,"color":"ff3f00ff"},{"name":"R_leg","parent":"body6","length":85.63,"rotation":69.74,"x":85.22,"y":-0.2,"color":"ff3f00ff"},{"name":"move_cp","parent":"root","x":-79.03,"y":-11.23},{"name":"R_foot","parent":"move_cp","length":73.08,"rotation":-177.95,"x":2.66,"y":59.35,"color":"ff3f00ff"},{"name":"body7","parent":"body3","length":63.74,"rotation":-158.76,"x":45.62,"y":-62.3,"color":"0dff37ff"},{"name":"L_leg","parent":"body7","length":90.09,"rotation":6.51,"x":63.03,"y":-0.09,"color":"0dff37ff"},{"name":"move_ct","parent":"root","x":119.83,"y":-11.23},{"name":"L_foot","parent":"move_ct","length":55.93,"rotation":-177.44,"x":3.13,"y":57.68,"color":"0dff37ff"},{"name":"body8","parent":"body3","length":86.5,"rotation":137.58,"x":43.55,"y":-62.74,"color":"6c00ffff"},{"name":"R_leg2","parent":"body8","length":85.63,"rotation":69.74,"x":85.22,"y":-0.2,"color":"6c00ffff"},{"name":"R_foot2","parent":"move_ct","length":73.08,"rotation":-177.95,"x":-0.6,"y":59.35,"color":"6c00ffff"},{"name":"fx1/1","parent":"root","length":99.54,"rotation":89.27,"x":286.91,"y":3.6},{"name":"fx2/s1","parent":"root","length":458.3,"rotation":0.57,"x":275,"y":0.09},{"name":"fx2/s2","parent":"root","length":458.3,"rotation":0.57,"x":275,"y":0.09},{"name":"fx3/fx1 (00)","parent":"root","rotation":0.88,"x":-488.17,"y":258.16,"scaleX":-1},{"name":"box_attack","parent":"root","x":-676.27,"y":73.54},{"name":"angry","parent":"eye","x":40.86,"y":-1.37,"transform":"noScale","color":"ff0000ff"},{"name":"smile","parent":"eye","x":-56.43,"y":-6.09,"transform":"noScale","color":"ff0000ff"}],"slots":[{"name":"weapon2","bone":"weapon2","dark":"000000","attachment":"weapon"},{"name":"R_forearm","bone":"R_forearm","dark":"000000","attachment":"R_forearm"},{"name":"R_hand","bone":"R_hand","dark":"000000","attachment":"R_hand"},{"name":"R_arm","bone":"R_arm","dark":"000000","attachment":"R_arm"},{"name":"L_leg","bone":"L_leg","dark":"000000","attachment":"L_leg"},{"name":"L_foot","bone":"L_foot","dark":"000000","attachment":"L_foot"},{"name":"R_leg","bone":"R_leg","dark":"000000","attachment":"R_leg"},{"name":"R_leg2","bone":"R_leg2","dark":"000000"},{"name":"R_foot","bone":"R_foot","dark":"000000","attachment":"R_foot"},{"name":"R_foot2","bone":"R_foot2","dark":"000000"},{"name":"skirt","bone":"body3","dark":"000000","attachment":"skirt"},{"name":"body","bone":"body3","dark":"000000","attachment":"body"},{"name":"head","bone":"head","dark":"000000","attachment":"head"},{"name":"eye","bone":"eye","dark":"000000","attachment":"eye"},{"name":"dot","bone":"dot","dark":"000000","attachment":"dot"},{"name":"angry","bone":"angry","dark":"000000","attachment":"angry"},{"name":"smile","bone":"smile","dark":"000000","attachment":"smile"},{"name":"weapon","bone":"weapon","dark":"000000","attachment":"weapon"},{"name":"L_hand","bone":"L_hand","dark":"000000","attachment":"L_hand"},{"name":"L_forearm","bone":"L_forearm","dark":"000000","attachment":"L_forearm"},{"name":"L_arm","bone":"L_arm","dark":"000000","attachment":"L_arm"},{"name":"fx1/1","bone":"fx1/1"},{"name":"fx2/s1","bone":"fx2/s1"},{"name":"fx2/s2","bone":"fx2/s2"},{"name":"fx3/fx1 (00)","bone":"fx3/fx1 (00)","blend":"additive"},{"name":"box_attack","bone":"box_attack"}],"ik":[{"name":"R_foot","bones":["body6","R_leg"],"target":"R_foot","stretch":true},{"name":"R_foot2","order":2,"bones":["body8","R_leg2"],"target":"R_foot2","stretch":true},{"name":"bone","order":1,"bones":["body7","L_leg"],"target":"L_foot","stretch":true}],"skins":[{"name":"default","attachments":{"L_foot":{"L_foot":{"x":14.42,"y":7.26,"rotation":177.44,"width":111,"height":80}},"L_hand":{"L_hand":{"x":36.29,"y":-7.29,"rotation":79.56,"width":114,"height":108}},"angry":{"angry":{"x":6.04,"y":1.07,"rotation":-93.43,"width":48,"height":29}},"smile":{"smile":{"x":8.31,"y":-0.04,"rotation":-93.43,"width":59,"height":36}},"dot":{"dot":{"x":-0.59,"y":-0.02,"rotation":-134.69,"width":12,"height":14}},"fx3/fx1 (00)":{"fx3/fx1 (00)":{"x":28.45,"y":-2.44,"width":191,"height":161},"fx3/fx1 (01)":{"x":16.33,"y":-4.14,"width":203,"height":155},"fx3/fx1 (02)":{"x":8.23,"y":-11.62,"width":215,"height":134},"fx3/fx1 (03)":{"x":6.49,"y":-36.9,"width":220,"height":90},"fx3/fx1 (04)":{"x":-1.61,"y":-60.43,"width":212,"height":44}},"skirt":{"skirt":{"type":"mesh","uvs":[0,0.67473,0.08201,0.38045,0.19422,0.14102,0.36704,0,0.49027,0,0.64046,0,0.82102,0.09863,0.92807,0.31061,0.97063,0.61238,1,0.77699,1,0.9391,0.85396,0.94048,0.62627,0.94264,0.51226,1,0.40763,1,0.30642,0.97257,0.13044,0.96337,0,0.95655,0.30584,0.74923,0.62182,0.74174,0.31358,0.46242,0.61279,0.46741,0.3368,0.19307,0.61022,0.19556,0.73556,0.16405,0.78228,0.42374,0.82026,0.69453,0.25241,0.16426,0.1849,0.43436,0.14432,0.72923,0.45796,0.76798,0.46069,0.47732,0.47221,0.20674],"triangles":[21,24,25,19,21,25,25,6,7,25,7,8,26,25,8,19,25,26,26,8,9,9,11,26,10,11,9,12,26,11,12,19,26,19,31,21,20,22,31,18,20,31,30,18,31,19,30,31,13,30,19,14,15,18,29,18,15,12,13,19,30,14,18,13,14,30,31,32,21,25,24,6,20,27,22,24,5,6,22,27,3,27,2,3,23,4,5,23,5,24,32,3,4,32,4,23,22,3,32,32,23,21,28,2,27,31,22,32,21,23,24,28,1,2,28,27,20,29,1,28,0,1,29,18,28,20,29,28,18,17,0,29,16,17,29,16,29,15],"vertices":[1,15,96.31,-23.56,1,1,15,35.4,-31.38,1,1,2,86.71,97.15,1,1,2,107.6,45.76,1,1,2,109.15,6.24,1,1,2,111.04,-41.94,1,1,2,101,-87.49,1,1,16,-0.08,24.05,1,1,16,62.03,20.75,1,1,16,97.81,18.65,1,1,16,122.74,8.53,1,2,17,95.89,106,0.16884,16,104.95,-45.84,0.83116,1,17,104.47,17.22,1,1,17,104.83,3.96,1,1,17,105.36,-15.16,1,2,15,81.83,95.85,0.30645,17,106.29,-49.41,0.69355,2,15,111.95,41.28,0.86942,17,103.84,-111.69,0.13058,2,15,134.28,0.82,0.99995,17,102.03,-157.86,5.0E-5,2,15,48.4,80.06,0.28909,17,69.51,-45.63,0.71091,1,17,71.88,19.46,1,2,15,6.76,48.33,0.43889,17,17.46,-51.25,0.56111,2,17,19.92,23.46,0.21539,16,2.26,-90.98,0.78461,1,2,78.44,50.36,1,1,2,73.66,-28.48,1,1,2,89.58,-62.84,1,2,17,-5.04,77.47,0.00723,16,1.05,-31.5,0.99277,2,17,48.44,92.16,0.13672,16,55.93,-39.49,0.86328,1,2,82.9,75.58,1,2,15,20.92,8.92,0.95427,17,9.2,-92.3,0.04573,2,15,72.49,27.96,0.86381,17,63.18,-102.68,0.13619,1,17,70.68,-13.5,1,1,17,18.66,-14.84,1,1,2,76.14,12.43,1],"hull":18,"edges":[0,2,2,4,4,6,10,12,12,14,14,16,16,18,18,20,0,34,28,30,24,26,26,28,12,48,48,46,14,50,50,42,16,52,52,38,20,22,22,24,4,54,54,44,2,56,56,40,0,58,58,36,30,32,32,34,36,60,60,38,40,62,62,42,44,64,64,46,6,8,8,10],"width":321,"height":166}},"R_hand":{"R_hand":{"x":25.93,"y":-13.15,"rotation":154.92,"width":108,"height":117},"R_hand_throw":{"x":41.72,"y":-18.33,"rotation":154.92,"width":147,"height":171}},"weapon2":{"weapon":{"x":50.12,"y":19.96,"rotation":144.56,"width":222,"height":220}},"R_foot2":{"R_foot":{"x":24.54,"y":7.69,"rotation":177.95,"width":124,"height":82}},"L_leg":{"L_leg":{"x":31.81,"y":0.01,"rotation":64.5,"width":107,"height":119}},"weapon":{"weapon":{"x":53.92,"y":16.18,"rotation":145.79,"width":222,"height":220}},"fx1/1":{"fx1/1":{"x":104.47,"y":4.28,"rotation":-89.27,"width":398,"height":221},"fx1/2":{"x":104.47,"y":4.28,"rotation":-89.27,"width":398,"height":221},"fx1/3 (1)":{"x":104.47,"y":4.28,"rotation":-89.27,"width":398,"height":221},"fx1/4 (1)":{"x":104.47,"y":4.28,"rotation":-89.27,"width":398,"height":221},"fx1/5 (1)":{"x":104.47,"y":4.28,"rotation":-89.27,"width":398,"height":221},"fx1/6 (1)":{"x":104.47,"y":4.28,"rotation":-89.27,"width":398,"height":221},"fx1/7":{"x":104.47,"y":4.28,"rotation":-89.27,"width":398,"height":221}},"head":{"head":{"x":46.38,"y":6.91,"rotation":-134.69,"width":166,"height":166},"head2":{"x":46.38,"y":6.91,"rotation":-134.62,"width":166,"height":166}},"R_leg":{"R_leg":{"x":33.14,"y":0.54,"rotation":64.93,"width":95,"height":109}},"body":{"body":{"type":"mesh","uvs":[0,0.69145,0,0.83263,0.27759,1,0.58946,0.99851,0.86566,0.93542,1,0.76324,1,0.64382,1,0.49307,0.97787,0.37873,0.95739,0.2729,0.93448,0.14501,0.84284,0.04302,0.72828,0,0.55732,0,0.44453,0,0.31255,0.0519,0.16783,0.16929,0.09557,0.29881,0.04848,0.42059,0,0.54598,0.52098,0.58361,0.55878,0.84487,0.20601,0.58252,0.22289,0.8404,0.80336,0.55463,0.83459,0.80447,0.24202,0.31197,0.51595,0.3158,0.79479,0.30337,0.20519,0.70932,0.53416,0.71527,0.81776,0.68401,0.21815,0.43244,0.50986,0.44137,0.7967,0.41904],"triangles":[28,12,11,28,11,10,28,10,9,26,16,15,17,16,26,27,14,13,15,14,27,26,15,27,27,13,12,28,27,12,28,9,8,34,28,8,27,28,34,32,17,26,18,17,32,33,26,27,33,27,34,32,26,33,34,8,7,24,34,7,33,34,24,22,18,32,19,18,22,20,33,24,24,7,6,20,24,31,22,33,20,33,22,32,20,29,22,0,19,22,31,24,6,29,0,22,31,6,5,25,31,5,1,0,29,23,29,30,1,29,23,21,30,31,21,31,25,23,30,21,4,25,5,4,3,21,4,21,25,2,23,21,2,21,3,1,23,2,30,20,31,29,20,30],"vertices":[2,2,88.46,144.91,0.60435,3,-19.32,147.59,0.39565,1,2,44.43,143.18,1,2,2,-13.72,77.12,0.97747,3,-127.79,90.41,0.02253,1,2,-9.48,-31.14,1,1,2,12.11,-97.94,1,1,2,62.44,-138.33,1,2,2,109.74,-136.47,0.69971,3,-26.39,-134.5,0.30029,2,2,162.26,-134.42,0.36636,3,26.07,-137.73,0.63364,2,2,185.24,-127.79,0.25151,3,49.6,-133.44,0.74849,2,2,206.52,-121.65,0.1452,3,71.39,-129.47,0.8548,2,2,256.39,-112.23,0.02912,3,121.95,-125.11,0.97088,2,2,286.66,-85.18,0.00442,3,154.78,-101.23,0.99558,1,3,169.95,-69.8,1,1,3,172.9,-21.68,1,1,3,174.86,10.07,1,1,3,158.81,53.38,1,2,2,240.46,103.5,0.01738,3,127.77,91.14,0.98262,2,2,199.94,122.31,0.1025,3,89.33,113.91,0.8975,2,2,167.36,134.32,0.25293,3,58.13,129.14,0.74707,2,2,133.82,146.69,0.40782,3,26,144.81,0.59218,2,2,131.4,-18.75,0.30603,3,6.98,-19.55,0.69397,1,2,38.72,-26.9,1,2,2,132.88,82.32,0.36049,3,18.6,80.86,0.63951,1,2,42.17,75.88,1,2,2,151.3,-93.34,0.38211,3,19.29,-95.76,0.61789,1,2,54.2,-99.62,1,2,2,198.16,76.23,0.04819,3,82.93,68.25,0.95181,2,2,199.22,-12.79,0.00303,3,75.05,-20.42,0.99697,2,2,213.69,-75.99,0.06735,3,83.11,-84.76,0.93265,2,2,88.02,81.95,0.80625,3,-26.07,85,0.19375,2,2,84.49,-17.17,0.7959,3,-39.54,-13.27,0.2041,2,2,100.02,-92.03,0.69993,3,-31.6,-89.31,0.30007,2,2,168.81,80,0.18966,3,54.12,74.94,0.81034,2,2,166.64,-12.43,0.15032,3,42.67,-16.8,0.84968,2,2,183.55,-79.57,0.20976,3,52.75,-85.3,0.79024],"hull":20,"edges":[2,4,4,6,6,8,8,10,18,20,20,22,22,24,28,30,30,32,32,34,24,26,26,28,2,0,0,38,10,12,12,14,34,36,36,38,14,16,16,18],"width":282,"height":307}},"L_arm":{"L_arm":{"x":70.94,"y":1.69,"rotation":43.69,"width":176,"height":163}},"fx2/s1":{"fx2/s1":{"x":200.03,"y":157.06,"rotation":-0.57,"width":534,"height":320},"fx2/s2":{"x":200.03,"y":157.06,"rotation":-0.57,"width":534,"height":320},"fx2/s3":{"x":200.03,"y":157.06,"rotation":-0.57,"width":534,"height":320},"fx2/s4":{"x":200.03,"y":157.06,"rotation":-0.57,"width":534,"height":320},"fx2/s5":{"x":200.03,"y":157.06,"rotation":-0.57,"width":534,"height":320},"fx2/s6":{"x":200.03,"y":157.06,"rotation":-0.57,"width":534,"height":320},"fx2/s7":{"x":200.03,"y":157.06,"rotation":-0.57,"width":534,"height":320},"fx2/s8":{"x":200.03,"y":157.06,"rotation":-0.57,"width":534,"height":320},"fx2/s9":{"x":200.03,"y":157.06,"rotation":-0.57,"width":534,"height":320},"fx2/s99":{"x":200.03,"y":157.06,"rotation":-0.57,"width":534,"height":320},"fx2/s999":{"x":200.03,"y":157.06,"rotation":-0.57,"width":534,"height":320}},"L_forearm":{"L_forearm":{"x":35.65,"y":-3.27,"rotation":72.24,"width":107,"height":135}},"eye":{"eye":{"x":-0.81,"y":-2.46,"rotation":-93.43,"width":64,"height":56}},"R_arm":{"R_arm":{"x":76.89,"y":3.16,"rotation":136.14,"width":156,"height":160}},"R_leg2":{"R_leg":{"x":33.14,"y":0.54,"rotation":64.93,"width":95,"height":109}},"R_forearm":{"R_forearm":{"x":33.61,"y":-1.28,"rotation":165.12,"width":135,"height":107}},"R_foot":{"R_foot":{"x":24.54,"y":7.69,"rotation":177.95,"width":124,"height":82}},"box_attack":{"box_attack":{"type":"boundingbox","vertexCount":4,"vertices":[-73.09,75.66,-72.64,-73.34,76.35,-72.84,75.84,76.67]}},"fx2/s2":{"fx2/s1":{"x":200.03,"y":157.06,"rotation":-0.57,"width":534,"height":320},"fx2/s2":{"x":200.03,"y":157.06,"rotation":-0.57,"width":534,"height":320},"fx2/s3":{"x":200.03,"y":157.06,"rotation":-0.57,"width":534,"height":320},"fx2/s4":{"x":200.03,"y":157.06,"rotation":-0.57,"width":534,"height":320},"fx2/s5":{"x":200.03,"y":157.06,"rotation":-0.57,"width":534,"height":320},"fx2/s6":{"x":200.03,"y":157.06,"rotation":-0.57,"width":534,"height":320},"fx2/s7":{"x":200.03,"y":157.06,"rotation":-0.57,"width":534,"height":320},"fx2/s8":{"x":200.03,"y":157.06,"rotation":-0.57,"width":534,"height":320},"fx2/s9":{"x":200.03,"y":157.06,"rotation":-0.57,"width":534,"height":320},"fx2/s99":{"x":200.03,"y":157.06,"rotation":-0.57,"width":534,"height":320},"fx2/s999":{"x":200.03,"y":157.06,"rotation":-0.57,"width":534,"height":320}}}}],"events":{"AttackComplete":{},"SkillComplete":{}},"animations":{"attack":{"slots":{"fx3/fx1 (00)":{"attachment":[{"time":0.8667,"name":"fx3/fx1 (00)"},{"time":0.9,"name":"fx3/fx1 (01)"},{"time":0.9333,"name":"fx3/fx1 (02)"},{"time":0.9667,"name":"fx3/fx1 (03)"},{"time":1,"name":"fx3/fx1 (04)"},{"time":1.0333,"name":null}]},"box_attack":{"attachment":[{"time":0.8667,"name":"box_attack"},{"time":1,"name":null}]}},"bones":{"R_leg2":{"rotate":[{"angle":-9.73}]},"L_leg":{"rotate":[{}]},"body8":{"rotate":[{"angle":36.54}]},"move_body":{"translate":[{"curve":0.25,"c3":0.15},{"time":0.6667,"x":30.87,"curve":0.25,"c3":0.173},{"time":0.9,"x":-48.05,"curve":0.25,"c3":0.75},{"time":1.2667,"x":15.02,"curve":0.25,"c3":0.75},{"time":1.6667}]},"body3":{"rotate":[{"curve":0.25,"c3":0.15},{"time":0.7,"angle":-9.15,"curve":0.25,"c3":0.158,"c4":0.99},{"time":0.9333,"angle":22.08,"curve":0.25,"c3":0.75},{"time":1.6667}],"translate":[{"curve":0.25,"c3":0.15},{"time":0.6667,"y":-0.18,"curve":0.25,"c3":0.158,"c4":0.99},{"time":0.9,"y":-35.75,"curve":0.25,"c3":0.75},{"time":1.6667}]},"body4":{"rotate":[{"angle":0.67,"curve":0.25,"c3":0.15},{"time":0.7333,"angle":-22.29,"curve":0.25,"c3":0.154},{"time":0.9667,"angle":29.88,"curve":0.25,"c3":0.75},{"time":1.6667,"angle":0.67}],"translate":[{"x":-0.59,"y":-0.02}]},"head":{"rotate":[{"angle":-2.2,"curve":0.25,"c3":0.15},{"time":0.8,"angle":-24.7,"curve":0.466,"c3":0.65,"c4":0.47},{"time":0.9,"angle":-34.03,"curve":0.139,"c2":0.46,"c3":0.367},{"time":1.0333,"angle":-15.6,"curve":0.25,"c3":0.75},{"time":1.6667,"angle":-2.2}]},"dot":{"translate":[{"x":-2.21,"y":1.67,"curve":0.25,"c3":0.162},{"time":0.8,"x":10.4,"y":2.91,"curve":0.454,"c3":0.648,"c4":0.47},{"time":0.9333,"x":-0.06,"y":2.04,"curve":0.145,"c2":0.46,"c3":0.376},{"time":1.0667,"x":-1.11,"y":4.13,"curve":0.25,"c3":0.75},{"time":1.1667,"x":4.78,"y":6.36,"curve":0.25,"c3":0.75},{"time":1.6667,"x":-2.21,"y":1.67}]},"L_arm":{"rotate":[{"angle":0.16,"curve":0.456,"c3":0.697,"c4":0.43},{"time":0.1667,"angle":-71,"curve":0.134,"c2":0.41,"c3":0.32},{"time":0.8,"angle":170.87,"curve":0.25,"c3":0.75},{"time":0.8333,"angle":166.18,"curve":0.25,"c3":0.625,"c4":0.5},{"time":0.8667,"angle":-143.23,"curve":0.25,"c3":0.165},{"time":0.9,"angle":-11.6,"curve":0.25,"c3":0.75},{"time":1.0667,"angle":-9.55,"curve":0.25,"c3":0.75},{"time":1.6667,"angle":0.16}],"translate":[{"curve":0.25,"c3":0.173},{"time":0.7667,"x":-16.02,"y":5,"curve":0.25,"c3":0.75},{"time":0.8667}],"scale":[{"time":0.8,"curve":0.25,"c3":0.75},{"time":0.8333,"x":1.573,"curve":0.25,"c3":0.177},{"time":0.8667}]},"L_forearm":{"rotate":[{"angle":-2.04,"curve":0.246,"c3":0.75},{"time":0.2333,"angle":13.36,"curve":0.247,"c3":0.727,"c4":0.9},{"time":0.8,"angle":-73.05,"curve":0.35,"c2":0.65,"c3":0.684},{"time":0.8333,"angle":0.12,"curve":0.25,"c3":0.75},{"time":0.9333,"angle":21.09,"curve":0.25,"c3":0.75},{"time":1.1,"angle":23.14,"curve":0.25,"c3":0.75},{"time":1.6667,"angle":-2.04}]},"L_hand":{"rotate":[{"angle":-1.67,"curve":0.25,"c3":0.75},{"time":0.3,"angle":44.16,"curve":0.25,"c3":0.75},{"time":0.8,"angle":-20.18,"curve":0.25,"c3":0.75},{"time":0.8333,"angle":39.12,"curve":0.25,"c3":0.146},{"time":0.9,"angle":55.48,"curve":0.25,"c3":0.75},{"time":1.1333,"angle":57.2,"curve":0.25,"c3":0.75},{"time":1.6667,"angle":-1.67}]},"R_arm":{"rotate":[{"angle":0.16,"curve":0.25,"c3":0.75},{"time":0.8,"angle":-116.99,"curve":0.25,"c3":0.75},{"time":0.8333,"angle":-132.61,"curve":0.25,"c3":0.75},{"time":0.8667,"angle":-93.33,"curve":0.25,"c3":0.165},{"time":0.9,"angle":60.53,"curve":0.25,"c3":0.75},{"time":1.0667,"angle":62.58,"curve":0.25,"c3":0.75},{"time":1.6667,"angle":0.16}],"scale":[{"time":0.8,"curve":0.25,"c3":0.75},{"time":0.8333,"x":1.637,"curve":0.25,"c3":0.177},{"time":0.8667}]},"R_forearm":{"rotate":[{"angle":-1.21,"curve":0.246,"c3":0.75},{"time":0.2333,"angle":9.63,"curve":0.247,"c3":0.727,"c4":0.9},{"time":0.8,"angle":-83.19,"curve":0.35,"c2":0.65,"c3":0.684},{"time":0.8333,"angle":11.27,"curve":0.25,"c3":0.75},{"time":0.9333,"angle":14.88,"curve":0.25,"c3":0.75},{"time":1.1,"angle":16.92,"curve":0.25,"c3":0.75},{"time":1.6667,"angle":-1.21}]},"R_hand":{"rotate":[{"angle":-1.67,"curve":0.25,"c3":0.75},{"time":0.3,"angle":31.95,"curve":0.25,"c3":0.75},{"time":0.8,"angle":-21.62,"curve":0.25,"c3":0.75},{"time":0.8333,"angle":37.68,"curve":0.25,"c3":0.146},{"time":0.9,"angle":54.04,"curve":0.25,"c3":0.75},{"time":1.1333,"angle":55.76,"curve":0.25,"c3":0.75},{"time":1.6667,"angle":-1.67}]},"skirt":{"rotate":[{"angle":-0.61,"curve":0.25,"c3":0.15},{"time":0.6667,"angle":5.06,"curve":0.25,"c3":0.158,"c4":0.99},{"time":0.9,"angle":-26.32,"curve":0.25,"c3":0.75},{"time":1.1667,"angle":-34.7,"curve":0.25,"c3":0.75},{"time":1.5,"angle":0.58,"curve":0.25,"c3":0.75},{"time":1.6667,"angle":-0.61}]},"skirt2":{"rotate":[{"angle":4.32,"curve":0.25,"c3":0.15},{"time":0.6667,"angle":-7.96,"curve":0.25,"c3":0.75},{"time":0.8333,"angle":14.68,"curve":0.223,"c3":0.417,"c4":0.99},{"time":1.1,"angle":15.55,"curve":0.25,"c3":0.75},{"time":1.4333,"angle":-9.72,"curve":0.25,"c3":0.75},{"time":1.6667,"angle":4.32}]},"body5":{"rotate":[{"angle":-3.88}]},"body6":{"rotate":[{"angle":-0.54}]},"R_leg":{"rotate":[{"angle":0.96}]},"fx3/fx1 (00)":{"rotate":[{},{"time":0.8667,"angle":12.82}],"translate":[{},{"time":0.8667,"x":377.82,"y":114.54}],"scale":[{},{"time":0.8667,"x":5.04,"y":4.018}]},"box_attack":{"translate":[{"time":0.8667,"x":305.23,"y":221.98}],"scale":[{"time":0.8667,"x":4.712,"y":3.646}]},"eye":{"rotate":[{},{"time":0.3,"angle":5.42,"curve":"stepped"},{"time":1.3,"angle":5.42},{"time":1.6}],"translate":[{},{"time":0.3,"x":-1.25,"y":6.48,"curve":"stepped"},{"time":1.3,"x":-1.25,"y":6.48},{"time":1.6}],"scale":[{},{"time":0.3,"x":-1,"curve":"stepped"},{"time":1.3,"x":-1},{"time":1.6}]}},"events":[{"time":1.6333,"name":"AttackComplete"}]},"die":{"slots":{"L_leg":{"attachment":[{"name":null}]},"R_leg2":{"attachment":[{"name":"R_leg"}]},"L_foot":{"attachment":[{"name":null}]},"R_foot2":{"attachment":[{"name":"R_foot"}]},"dot":{"attachment":[{"time":0.0333,"name":null}]},"smile":{"attachment":[{"time":0.0333,"name":null}]}},"bones":{"move_ct":{"translate":[{"curve":0.25,"c3":0.75},{"time":0.7,"x":-127.32}]},"body8":{"rotate":[{"angle":36.54}]},"R_leg2":{"rotate":[{"angle":-9.73}]},"move_body":{"translate":[{"curve":0.08,"c2":0.59,"c3":0.75},{"time":0.3333,"x":113.81}]},"body3":{"rotate":[{"curve":0.25,"c3":0.75},{"time":0.1667,"angle":5.73,"curve":0.25,"c3":0.75},{"time":0.3667,"curve":0.25,"c3":0.943,"c4":0.39},{"time":0.7,"angle":-87.12,"curve":0.088,"c2":0.6,"c3":0.75},{"time":0.9,"angle":-85.25,"curve":0.25,"c3":0.943,"c4":0.39},{"time":1.1,"angle":-87.12}],"translate":[{"curve":0.08,"c2":0.59,"c3":0.75},{"time":0.1333,"y":34.81,"curve":0.25,"c3":0.928,"c4":0.41},{"time":0.3333,"y":-98.79,"curve":0.084,"c2":0.59,"c3":0.75},{"time":0.5,"y":-66.35,"curve":0.25,"c3":0.935,"c4":0.41},{"time":0.6667,"y":-98.79}]},"body4":{"rotate":[{"angle":0.67,"curve":0.25,"c3":0.75},{"time":0.2,"angle":8.69,"curve":0.25,"c3":0.75},{"time":0.4,"angle":-6.02,"curve":0.25,"c3":0.943,"c4":0.39},{"time":0.7333,"angle":-19.5,"curve":0.088,"c2":0.6,"c3":0.75},{"time":0.9333,"angle":-12.77,"curve":0.25,"c3":0.943,"c4":0.39},{"time":1.1333,"angle":-19.5}],"translate":[{"x":-0.59,"y":-0.02}]},"head":{"rotate":[{"angle":-2.2,"curve":0.25,"c3":0.75},{"time":0.2333,"angle":24.82,"curve":0.25,"c3":0.75},{"time":0.4333,"angle":3,"curve":0.25,"c3":0.943,"c4":0.39},{"time":0.7667,"angle":-53.32,"curve":0.088,"c2":0.6,"c3":0.75},{"time":0.9667,"angle":-46.61,"curve":0.25,"c3":0.943,"c4":0.39},{"time":1.1667,"angle":-53.32}]},"dot":{"translate":[{"x":-2.21,"y":1.67}]},"L_arm":{"rotate":[{"angle":0.16,"curve":0.25,"c3":0.75},{"time":0.2333,"angle":-66.67,"curve":0.25,"c3":0.75},{"time":0.4333,"angle":-18.18,"curve":0.25,"c3":0.75},{"time":0.5333,"angle":-23.53,"curve":0.25,"c3":0.75},{"time":0.7333,"angle":-48.55,"curve":0.25,"c3":0.931,"c4":0.4},{"time":0.9,"angle":-24.63,"curve":0.088,"c2":0.59,"c3":0.75},{"time":1.0333,"angle":-33.07,"curve":0.25,"c3":0.931,"c4":0.4},{"time":1.1667,"angle":-24.63}]},"L_forearm":{"rotate":[{"angle":-2.04,"curve":0.25,"c3":0.75},{"time":0.2667,"angle":-10.34,"curve":0.25,"c3":0.75},{"time":0.4667,"angle":1.75,"curve":0.25,"c3":0.75},{"time":0.7667,"angle":-6.97,"curve":0.25,"c3":0.935,"c4":0.4},{"time":0.9333,"angle":30.01,"curve":0.076,"c2":0.59,"c3":0.75},{"time":1.0667,"angle":26.06,"curve":0.25,"c3":0.935,"c4":0.4},{"time":1.2,"angle":30.01}]},"L_hand":{"rotate":[{"angle":-1.67,"curve":0.25,"c3":0.75},{"time":0.3,"angle":-9.18,"curve":0.25,"c3":0.75},{"time":0.5,"angle":10.63,"curve":0.25,"c3":0.75},{"time":0.8,"angle":3.66,"curve":0.25,"c3":0.928,"c4":0.41},{"time":0.9667,"angle":52.69,"curve":0.08,"c2":0.59,"c3":0.75},{"time":1.1,"angle":48.21,"curve":0.25,"c3":0.928,"c4":0.41},{"time":1.2,"angle":52.69}]},"R_arm":{"rotate":[{"angle":0.16,"curve":0.25,"c3":0.75},{"time":0.2333,"angle":-39.48,"curve":0.25,"c3":0.75},{"time":0.4333,"angle":25.1,"curve":0.25,"c3":0.75},{"time":0.5333,"angle":19.76,"curve":0.25,"c3":0.75},{"time":0.7333,"angle":-5.26,"curve":0.25,"c3":0.931,"c4":0.4},{"time":0.9,"angle":41.2,"curve":0.088,"c2":0.59,"c3":0.75},{"time":1.0333,"angle":19.87,"curve":0.25,"c3":0.931,"c4":0.4},{"time":1.1667,"angle":41.2}]},"R_forearm":{"rotate":[{"angle":-1.21,"curve":0.25,"c3":0.75},{"time":0.2667,"angle":-9.51,"curve":0.25,"c3":0.75},{"time":0.4667,"angle":2.57,"curve":0.25,"c3":0.75},{"time":0.7667,"angle":-6.14,"curve":0.25,"c3":0.935,"c4":0.4},{"time":0.9333,"angle":30.83,"curve":0.076,"c2":0.59,"c3":0.75},{"time":1.0667,"angle":26.89,"curve":0.25,"c3":0.935,"c4":0.4},{"time":1.2,"angle":30.83}]},"R_hand":{"rotate":[{"angle":-1.67,"curve":0.25,"c3":0.75},{"time":0.3,"angle":-9.18,"curve":0.25,"c3":0.75},{"time":0.5,"angle":10.63,"curve":0.25,"c3":0.75},{"time":0.8,"angle":3.66,"curve":0.25,"c3":0.928,"c4":0.41},{"time":0.9667,"angle":52.69,"curve":0.08,"c2":0.59,"c3":0.75},{"time":1.1,"angle":48.21,"curve":0.25,"c3":0.928,"c4":0.41},{"time":1.2,"angle":52.69}]},"skirt":{"rotate":[{"angle":-0.61}]},"skirt2":{"rotate":[{"angle":4.32}]},"body5":{"rotate":[{"angle":-3.88}]},"body6":{"rotate":[{"angle":-0.54}]},"R_leg":{"rotate":[{"angle":0.96}]},"move_cp":{"translate":[{"curve":0.25,"c3":0.75},{"time":0.3667,"x":14.61,"curve":0.25,"c3":0.75},{"time":0.7,"x":114.93}]},"R_foot":{"rotate":[{"curve":0.25,"c3":0.75},{"time":0.2,"angle":-5.5,"curve":0.25,"c3":0.935,"c4":0.4},{"time":0.4,"angle":-34.28,"curve":0.076,"c2":0.6,"c3":0.75},{"time":0.5333,"angle":-18.29,"curve":0.25,"c3":0.939,"c4":0.38},{"time":0.6667,"angle":-34.28}],"translate":[{"curve":0.25,"c3":0.75},{"time":0.1667,"y":53.24,"curve":0.25,"c3":0.931,"c4":0.4},{"time":0.3667,"y":-33.18,"curve":0.076,"c2":0.6,"c3":0.75},{"time":0.5,"y":-10.65,"curve":0.25,"c3":0.931,"c4":0.4},{"time":0.6333,"y":-33.18}]},"L_leg":{"rotate":[{}]},"R_foot2":{"rotate":[{"curve":0.25,"c3":0.75},{"time":0.2667,"angle":-4.71,"curve":0.25,"c3":0.935,"c4":0.4},{"time":0.4667,"angle":-28.62,"curve":0.076,"c2":0.6,"c3":0.75},{"time":0.6,"angle":-19.92,"curve":0.25,"c3":0.935,"c4":0.4},{"time":0.7333,"angle":-28.62}],"translate":[{"curve":0.25,"c3":0.75},{"time":0.2333,"y":65.65,"curve":0.25,"c3":0.931,"c4":0.4},{"time":0.4333,"y":-32.62,"curve":0.076,"c2":0.6,"c3":0.75},{"time":0.5667,"y":-19.69,"curve":0.25,"c3":0.931,"c4":0.4},{"time":0.7,"y":-32.62}]},"eye":{"translate":[{},{"time":0.1,"x":-6.16,"y":6.55}],"scale":[{},{"time":0.1,"x":0}]}}},"get_hurt":{"slots":{"eye":{"twoColor":[{"light":"ffffffff","dark":"8a8a8a","curve":"stepped"},{"time":0.1,"light":"ffffffff","dark":"8a8a8a"},{"time":0.1667,"light":"ffffffff","dark":"000000"}]},"angry":{"twoColor":[{"light":"ffffffff","dark":"8a8a8a","curve":"stepped"},{"time":0.1,"light":"ffffffff","dark":"8a8a8a"},{"time":0.1667,"light":"ffffffff","dark":"000000"}]},"L_leg":{"twoColor":[{"light":"ffffffff","dark":"8a8a8a","curve":"stepped"},{"time":0.1,"light":"ffffffff","dark":"8a8a8a"},{"time":0.1667,"light":"ffffffff","dark":"000000"}]},"R_leg2":{"twoColor":[{"light":"ffffffff","dark":"8a8a8a","curve":"stepped"},{"time":0.1,"light":"ffffffff","dark":"8a8a8a"},{"time":0.1667,"light":"ffffffff","dark":"000000"}]},"L_arm":{"twoColor":[{"light":"ffffffff","dark":"8a8a8a","curve":"stepped"},{"time":0.1,"light":"ffffffff","dark":"8a8a8a"},{"time":0.1667,"light":"ffffffff","dark":"000000"}]},"L_forearm":{"twoColor":[{"light":"ffffffff","dark":"8a8a8a","curve":"stepped"},{"time":0.1,"light":"ffffffff","dark":"8a8a8a"},{"time":0.1667,"light":"ffffffff","dark":"000000"}]},"L_hand":{"twoColor":[{"light":"ffffffff","dark":"8a8a8a","curve":"stepped"},{"time":0.1,"light":"ffffffff","dark":"8a8a8a"},{"time":0.1667,"light":"ffffffff","dark":"000000"}]},"weapon":{"twoColor":[{"light":"ffffffff","dark":"8a8a8a","curve":"stepped"},{"time":0.1,"light":"ffffffff","dark":"8a8a8a"},{"time":0.1667,"light":"ffffffff","dark":"000000"}]},"L_foot":{"twoColor":[{"light":"ffffffff","dark":"8a8a8a","curve":"stepped"},{"time":0.1,"light":"ffffffff","dark":"8a8a8a"},{"time":0.1667,"light":"ffffffff","dark":"000000"}]},"R_foot2":{"twoColor":[{"light":"ffffffff","dark":"8a8a8a","curve":"stepped"},{"time":0.1,"light":"ffffffff","dark":"8a8a8a"},{"time":0.1667,"light":"ffffffff","dark":"000000"}]},"skirt":{"twoColor":[{"light":"ffffffff","dark":"8a8a8a","curve":"stepped"},{"time":0.1,"light":"ffffffff","dark":"8a8a8a"},{"time":0.1667,"light":"ffffffff","dark":"000000"}]},"R_forearm":{"twoColor":[{"light":"ffffffff","dark":"8a8a8a","curve":"stepped"},{"time":0.1,"light":"ffffffff","dark":"8a8a8a"},{"time":0.1667,"light":"ffffffff","dark":"000000"}]},"R_arm":{"twoColor":[{"light":"ffffffff","dark":"8a8a8a","curve":"stepped"},{"time":0.1,"light":"ffffffff","dark":"8a8a8a"},{"time":0.1667,"light":"ffffffff","dark":"000000"}]},"R_hand":{"twoColor":[{"light":"ffffffff","dark":"8a8a8a","curve":"stepped"},{"time":0.1,"light":"ffffffff","dark":"8a8a8a"},{"time":0.1667,"light":"ffffffff","dark":"000000"}]},"R_leg":{"twoColor":[{"light":"ffffffff","dark":"8a8a8a","curve":"stepped"},{"time":0.1,"light":"ffffffff","dark":"8a8a8a"},{"time":0.1667,"light":"ffffffff","dark":"000000"}]},"body":{"twoColor":[{"light":"ffffffff","dark":"8a8a8a","curve":"stepped"},{"time":0.1,"light":"ffffffff","dark":"8a8a8a"},{"time":0.1667,"light":"ffffffff","dark":"000000"}]},"dot":{"twoColor":[{"light":"ffffffff","dark":"8a8a8a","curve":"stepped"},{"time":0.1,"light":"ffffffff","dark":"8a8a8a"},{"time":0.1667,"light":"ffffffff","dark":"000000"}]},"head":{"twoColor":[{"light":"ffffffff","dark":"8a8a8a","curve":"stepped"},{"time":0.1,"light":"ffffffff","dark":"8a8a8a"},{"time":0.1667,"light":"ffffffff","dark":"000000"}]},"weapon2":{"twoColor":[{"light":"ffffffff","dark":"8a8a8a","curve":"stepped"},{"time":0.1,"light":"ffffffff","dark":"8a8a8a"},{"time":0.1667,"light":"ffffffff","dark":"000000"}]},"smile":{"twoColor":[{"light":"ffffffff","dark":"8a8a8a","curve":"stepped"},{"time":0.1,"light":"ffffffff","dark":"8a8a8a"},{"time":0.1667,"light":"ffffffff","dark":"000000"}]},"R_foot":{"twoColor":[{"light":"ffffffff","dark":"8a8a8a","curve":"stepped"},{"time":0.1,"light":"ffffffff","dark":"8a8a8a"},{"time":0.1667,"light":"ffffffff","dark":"000000"}]}}},"idle":{"bones":{"body3":{"translate":[{"curve":0.25,"c3":0.75},{"time":0.6667,"y":-8.46,"curve":0.25,"c3":0.75},{"time":1.3333}]},"body4":{"rotate":[{"angle":0.67,"curve":0.375,"c2":0.62,"c3":0.716},{"time":0.1333,"curve":0.25,"c3":0.75},{"time":0.8,"angle":5.15,"curve":0.243,"c3":0.68,"c4":0.71},{"time":1.3333,"angle":0.67}],"translate":[{"x":-0.59,"y":-0.02,"curve":0.36,"c2":0.64,"c3":0.695},{"time":0.0667,"curve":0.25,"c3":0.75},{"time":0.7333,"x":-13.98,"y":-0.55,"curve":0.245,"c3":0.711,"c4":0.83},{"time":1.3333,"x":-0.59,"y":-0.02}]},"head":{"rotate":[{"angle":-2.2,"curve":0.382,"c2":0.58,"c3":0.731},{"time":0.2,"angle":-4.38,"curve":0.25,"c3":0.75},{"time":0.8667,"angle":4.6,"curve":0.243,"c3":0.655,"c4":0.63},{"time":1.3333,"angle":-2.2}]},"dot":{"translate":[{"x":-1.55,"y":13.27,"curve":0.25,"c3":0.233},{"time":0.5,"x":2.18,"y":-22.24,"curve":0.25,"c3":0.233},{"time":1,"x":-15.16,"y":2.38,"curve":0.25,"c3":0.233},{"time":1.3333,"x":-1.55,"y":13.27}]},"L_arm":{"rotate":[{"angle":0.16,"curve":0.289,"c2":0.17,"c3":0.755},{"time":0.6,"angle":3.74,"curve":0.25,"c3":0.75},{"time":1.2667,"curve":0.305,"c3":0.64,"c4":0.36},{"time":1.3333,"angle":0.16}]},"L_forearm":{"rotate":[{"angle":-2.04,"curve":0.32,"c2":0.29,"c3":0.757},{"time":0.5333,"angle":-12.99,"curve":0.25,"c3":0.75},{"time":1.2,"curve":0.284,"c3":0.625,"c4":0.38},{"time":1.3333,"angle":-2.04}]},"L_hand":{"rotate":[{"angle":-1.67,"curve":0.354,"c2":0.41,"c3":0.756},{"time":0.4333,"angle":-5.49,"curve":0.25,"c3":0.75},{"time":1.1,"curve":0.263,"c3":0.618,"c4":0.43},{"time":1.3333,"angle":-1.67}]},"R_arm":{"rotate":[{"angle":0.16,"curve":0.289,"c2":0.17,"c3":0.755},{"time":0.6,"angle":3.74,"curve":0.25,"c3":0.75},{"time":1.2667,"curve":0.305,"c3":0.64,"c4":0.36},{"time":1.3333,"angle":0.16}]},"R_forearm":{"rotate":[{"angle":-1.21,"curve":0.32,"c2":0.29,"c3":0.757},{"time":0.5333,"angle":-9.31,"curve":0.25,"c3":0.75},{"time":1.2,"curve":0.284,"c3":0.625,"c4":0.38},{"time":1.3333,"angle":-1.21}]},"R_hand":{"rotate":[{"angle":-1.67,"curve":0.354,"c2":0.41,"c3":0.756},{"time":0.4333,"angle":-5.49,"curve":0.25,"c3":0.75},{"time":1.1,"curve":0.263,"c3":0.618,"c4":0.43},{"time":1.3333,"angle":-1.67}]},"skirt":{"rotate":[{"angle":-0.61,"curve":0.375,"c2":0.62,"c3":0.716},{"time":0.1333,"curve":0.25,"c3":0.75},{"time":0.8,"angle":-4.71,"curve":0.243,"c3":0.68,"c4":0.71},{"time":1.3333,"angle":-0.61}]},"skirt2":{"rotate":[{"angle":4.32,"curve":0.375,"c2":0.62,"c3":0.716},{"time":0.1333,"angle":5.2,"curve":0.25,"c3":0.75},{"time":0.8,"angle":-1.58,"curve":0.243,"c3":0.68,"c4":0.71},{"time":1.3333,"angle":4.32}]},"body5":{"rotate":[{"angle":-3.88,"curve":0.375,"c2":0.62,"c3":0.716},{"time":0.1333,"angle":-5.45,"curve":0.25,"c3":0.75},{"time":0.8,"angle":6.63,"curve":0.243,"c3":0.68,"c4":0.71},{"time":1.3333,"angle":-3.88}]},"body6":{"rotate":[{"angle":-0.54}]},"R_leg":{"rotate":[{"angle":0.96}]},"L_leg":{"rotate":[{}]},"body8":{"rotate":[{"angle":36.54}]},"R_leg2":{"rotate":[{"angle":-9.73}]},"eye":{"rotate":[{"angle":1.35,"curve":0.375,"c2":0.5,"c3":0.75},{"time":0.3333,"angle":-4.28,"curve":0.25,"c3":0.75},{"time":1,"angle":4.89,"curve":0.25,"c3":0.625,"c4":0.5},{"time":1.3333,"angle":1.35}],"translate":[{"x":-2.25,"y":-2.21,"curve":0.381,"c2":0.55,"c3":0.742},{"time":0.2667,"x":-4.12,"y":-4.25,"curve":0.25,"c3":0.75},{"time":0.9333,"x":0.96,"y":1.3,"curve":0.245,"c3":0.637,"c4":0.56},{"time":1.3333,"x":-2.25,"y":-2.21}]}}},"move":{"slots":{"L_leg":{"attachment":[{"name":null}]},"R_leg2":{"attachment":[{"name":"R_leg"}]},"L_foot":{"attachment":[{"name":null}]},"R_foot2":{"attachment":[{"name":"R_foot"}]}},"bones":{"L_leg":{"rotate":[{}]},"R_leg2":{"rotate":[{"angle":-9.73}]},"R_foot2":{"rotate":[{"angle":22.63,"curve":0.25,"c3":0.75},{"time":0.1333,"angle":22.46,"curve":0.25,"c3":0.75},{"time":0.4007,"angle":-7.19,"curve":0.25,"c3":0.927,"c4":0.39},{"time":0.5075,"curve":"stepped"},{"time":1.0685,"curve":0.25,"c3":0.75},{"time":1.3356,"angle":22.63}],"translate":[{"x":-4.3,"y":22.08,"curve":0.379,"c2":0.6,"c3":0.724},{"time":0.4007,"x":-0.93,"y":29.25,"curve":0.25,"c3":0.927,"c4":0.39},{"time":0.5075,"curve":"stepped"},{"time":1.0685,"curve":0.25,"c3":0.75},{"time":1.3356,"x":-4.3,"y":22.08}]},"body3":{"rotate":[{"angle":4.46}],"translate":[{"y":-26.38,"curve":0.612,"c3":0.75},{"time":0.4007,"y":1.49,"curve":0.25,"c3":0.388},{"time":0.6678,"y":-26.38,"curve":0.612,"c3":0.75},{"time":1.0685,"y":1.49,"curve":0.25,"c3":0.388},{"time":1.3356,"y":-26.38}]},"body4":{"rotate":[{"angle":3.15,"curve":0.375,"c2":0.5,"c3":0.75},{"time":0.1333,"angle":6.3,"curve":0.25,"c3":0.75},{"time":0.5343,"curve":0.25,"c3":0.75},{"time":0.8014,"angle":6.3,"curve":0.25,"c3":0.75},{"time":1.2021,"curve":0.25,"c3":0.625,"c4":0.5},{"time":1.3356,"angle":3.15}],"translate":[{"x":-17.36,"y":1.81,"curve":0.26,"c2":0.58,"c3":0.582,"c4":0.99},{"time":0.0801,"x":-19.24,"y":2.01,"curve":0.612,"c3":0.75},{"time":0.4808,"curve":0.25,"c3":0.388},{"time":0.748,"x":-19.24,"y":2.01,"curve":0.612,"c3":0.75},{"time":1.1486,"curve":0.312,"c3":0.526,"c4":0.62},{"time":1.3356,"x":-17.36,"y":1.81}]},"head":{"rotate":[{"angle":-6.62,"curve":0.345,"c2":0.37,"c3":0.757},{"time":0.187,"angle":-1.64,"curve":0.25,"c3":0.75},{"time":0.5877,"angle":-8.21,"curve":0.25,"c3":0.75},{"time":0.8548,"angle":-1.64,"curve":0.25,"c3":0.75},{"time":1.2555,"angle":-8.21,"curve":0.269,"c3":0.618,"c4":0.42},{"time":1.3356,"angle":-6.62}]},"dot":{"translate":[{"x":2.25,"y":2.86,"curve":0.293,"c2":0.18,"c3":0.755},{"time":0.2404,"x":-16.34,"y":6.52,"curve":0.25,"c3":0.75},{"time":0.6411,"x":12.63,"y":2.17,"curve":0.25,"c3":0.75},{"time":0.9082,"x":-16.34,"y":6.52,"curve":0.25,"c3":0.75},{"time":1.3089,"x":12.63,"y":2.17,"curve":0.25,"c3":0.75},{"time":1.3356,"x":2.25,"y":2.86}]},"L_arm":{"rotate":[{"angle":-55.93,"curve":0.25,"c3":0.75},{"time":0.6678,"angle":1.96,"curve":0.25,"c3":0.75},{"time":1.3356,"angle":-55.93}],"translate":[{"x":0.69,"y":-17.07,"curve":0.25,"c3":0.75},{"time":0.6678,"curve":0.25,"c3":0.75},{"time":1.3356,"x":0.69,"y":-17.07}]},"L_forearm":{"rotate":[{"angle":-12.27,"curve":0.364,"c2":0.64,"c3":0.7},{"time":0.0801,"angle":-13.76,"curve":0.25,"c3":0.75},{"time":0.748,"angle":11.69,"curve":0.244,"c3":0.704,"c4":0.81},{"time":1.3356,"angle":-12.27}]},"L_hand":{"rotate":[{"angle":-15.55,"curve":0.379,"c2":0.6,"c3":0.723},{"time":0.1603,"angle":-18.71,"curve":0.25,"c3":0.75},{"time":0.8281,"angle":-0.49,"curve":0.242,"c3":0.669,"c4":0.68},{"time":1.3356,"angle":-15.55}]},"R_arm":{"rotate":[{"angle":56.17,"curve":0.25,"c3":0.75},{"time":0.6678,"angle":-16.09,"curve":0.25,"c3":0.75},{"time":1.3356,"angle":56.17}],"translate":[{"x":10.82,"y":-2.24}]},"R_forearm":{"rotate":[{"angle":-17.37,"curve":0.364,"c2":0.64,"c3":0.7},{"time":0.0801,"angle":-17.22,"curve":0.25,"c3":0.75},{"time":0.748,"angle":-19.82,"curve":0.244,"c3":0.704,"c4":0.81},{"time":1.3356,"angle":-17.37}]},"R_hand":{"rotate":[{"angle":-11.92,"curve":0.379,"c2":0.6,"c3":0.723},{"time":0.1603,"angle":-10.26,"curve":0.25,"c3":0.75},{"time":0.8281,"angle":-19.82,"curve":0.242,"c3":0.669,"c4":0.68},{"time":1.3356,"angle":-11.92}]},"skirt":{"rotate":[{"angle":-21.27},{"time":0.5343,"angle":18.1,"curve":0.25,"c3":0.75},{"time":1.0685,"angle":-25.08,"curve":0.271,"c3":0.619,"c4":0.41},{"time":1.3356,"angle":-21.27}]},"skirt2":{"rotate":[{"angle":-5.69},{"time":0.4007,"angle":-22.75,"curve":0.25,"c3":0.75},{"time":1.2021,"curve":0.276,"c3":0.621,"c4":0.4},{"time":1.3356,"angle":-5.69}]},"body6":{"rotate":[{"angle":-0.54}]},"R_leg":{"rotate":[{"angle":0.96}]},"move_cp":{"translate":[{"x":-6.52,"curve":0.342,"c2":0.36,"c3":0.757},{"time":0.5343,"x":109.88,"curve":0.25,"c3":0.75},{"time":1.0685,"x":-50.76,"curve":0.271,"c3":0.619,"c4":0.41},{"time":1.3356,"x":-6.52}]},"R_foot":{"rotate":[{"angle":-0.42,"curve":"stepped"},{"time":0.4007,"angle":-0.42,"curve":0.25,"c3":0.625,"c4":0.5},{"time":0.6678,"angle":13.56,"curve":0.25,"c3":0.75},{"time":0.8014,"angle":20.18,"curve":0.25,"c3":0.75},{"time":1.0685,"angle":-9.91,"curve":0.25,"c3":0.935,"c4":0.39},{"time":1.1754,"angle":-0.42}],"translate":[{"y":-0.14,"curve":"stepped"},{"time":0.4007,"y":-0.14,"curve":0.25,"c3":0.625,"c4":0.5},{"time":0.6678,"y":11.46,"curve":0.347,"c2":0.38,"c3":0.694,"c4":0.76},{"time":1.0685,"y":31.41,"curve":0.25,"c3":0.935,"c4":0.39},{"time":1.1754,"y":-0.14}]},"body7":{"rotate":[{}]},"move_ct":{"translate":[{"x":9.08,"curve":0.333,"c2":0.33,"c3":0.758},{"time":0.4007,"x":-109.53,"curve":0.25,"c3":0.75},{"time":1.2021,"x":11.86,"curve":0.276,"c3":0.621,"c4":0.4},{"time":1.3356,"x":9.08}]},"body8":{"rotate":[{"angle":36.54}]}}},"skill1":{"slots":{"fx2/s1":{"attachment":[{"time":1.0333,"name":"fx2/s1"},{"time":1.0667,"name":"fx2/s2"},{"time":1.1,"name":"fx2/s3"},{"time":1.1333,"name":"fx2/s4"},{"time":1.1667,"name":"fx2/s5"},{"time":1.2,"name":"fx2/s6"},{"time":1.2333,"name":"fx2/s7"},{"time":1.2667,"name":"fx2/s8"},{"time":1.3,"name":"fx2/s9"},{"time":1.3333,"name":"fx2/s99"},{"time":1.3667,"name":"fx2/s999"},{"time":1.4,"name":null}]},"fx1/1":{"attachment":[{"time":1.1,"name":"fx1/1"},{"time":1.1333,"name":"fx1/2"},{"time":1.1667,"name":"fx1/3 (1)"},{"time":1.2,"name":"fx1/4 (1)"},{"time":1.2333,"name":"fx1/5 (1)"},{"time":1.2667,"name":"fx1/6 (1)"},{"time":1.3,"name":"fx1/7"},{"time":1.3333,"name":null}]},"box_attack":{"attachment":[{"time":1.1,"name":"box_attack"},{"time":1.2333,"name":null}]},"fx2/s2":{"attachment":[{"time":1.0333,"name":"fx2/s1"},{"time":1.0667,"name":"fx2/s2"},{"time":1.1,"name":"fx2/s3"},{"time":1.1333,"name":"fx2/s4"},{"time":1.1667,"name":"fx2/s5"},{"time":1.2,"name":"fx2/s6"},{"time":1.2333,"name":"fx2/s7"},{"time":1.2667,"name":"fx2/s8"},{"time":1.3,"name":"fx2/s9"},{"time":1.3333,"name":"fx2/s99"},{"time":1.3667,"name":"fx2/s999"},{"time":1.4,"name":null}]}},"bones":{"head":{"rotate":[{"angle":-2.2,"curve":0.25,"c3":0.75},{"time":0.2333,"angle":-16.9,"curve":0.25,"c3":0.167,"c4":0.99},{"time":0.7667,"angle":13.24,"curve":0.25,"c3":0.75},{"time":1.1,"angle":-42.15,"curve":0.25,"c3":0.75},{"time":1.1667,"angle":-10.34,"curve":0.25,"c3":0.75},{"time":1.2333,"angle":-18.78,"curve":0.25,"c3":0.75},{"time":1.5,"angle":-8.38,"curve":0.25,"c3":0.75},{"time":1.7667,"angle":-2.2}]},"L_arm":{"rotate":[{"angle":0.16,"curve":0.25,"c3":0.75},{"time":0.2333,"angle":-17.83,"curve":0.25,"c3":0.75},{"time":0.7667,"angle":27.93,"curve":0.459,"c3":0.668,"c4":0.45},{"time":0.9,"angle":-69.73,"curve":0.139,"c2":0.44,"c3":0.355},{"time":1.0333,"angle":138.34,"curve":0.25,"c3":0.75},{"time":1.0667,"angle":-119.27,"curve":0.25,"c3":0.935,"c4":0.37},{"time":1.1,"angle":-102.25,"curve":0.25,"c3":0.75},{"time":1.5,"angle":-47.97},{"time":1.7667,"angle":0.16}],"translate":[{"time":1.0333,"curve":0.391,"c3":0.931,"c4":0.39},{"time":1.1,"x":-15.65,"y":-6.13,"curve":0.25,"c3":0.75},{"time":1.5}],"scale":[{"time":0.9,"curve":0.25,"c3":0.75},{"time":0.9667,"x":2.058,"curve":0.25,"c3":0.947,"c4":0.39},{"time":1.0667}]},"skirt":{"rotate":[{"angle":-0.61,"curve":0.25,"c3":0.75},{"time":0.6667,"angle":-24.2,"curve":0.25,"c3":0.75},{"time":0.8,"angle":15.47,"curve":0.25,"c3":0.163,"c4":0.98},{"time":0.9667,"angle":-27.5,"curve":0.25,"c3":0.75},{"time":1.1,"angle":-78.91,"curve":0.25,"c3":0.75},{"time":1.3333,"angle":-30.44,"curve":0.25,"c3":0.75},{"time":1.7667,"angle":-0.61}]},"body8":{"rotate":[{"angle":36.54}]},"body4":{"rotate":[{"angle":0.67,"curve":0.25,"c3":0.167,"c4":0.99},{"time":0.7333,"angle":20.21,"curve":0.25,"c3":0.152},{"time":1.0667,"angle":-26.68,"curve":0.359,"c2":0.43,"c3":0.756},{"time":1.1333,"angle":20.95,"curve":0.25,"c3":0.75},{"time":1.2,"angle":11.31,"curve":0.25,"c3":0.75},{"time":1.4667,"angle":15.33,"curve":0.25,"c3":0.75},{"time":1.7667,"angle":0.67}],"translate":[{"x":-0.59,"y":-0.02,"curve":0.25,"c3":0.167,"c4":0.99},{"time":0.7,"x":-21.6,"y":-1.78,"curve":0.25,"c3":0.75},{"time":1.0333,"x":52.12,"y":4.85,"curve":0.25,"c3":0.75},{"time":1.1,"x":-60.14,"y":-14.3,"curve":0.25,"c3":0.75},{"time":1.1667,"x":-0.59,"y":-0.02}],"scale":[{"time":1.0333,"curve":0.25,"c3":0.75},{"time":1.1,"y":1.109,"curve":0.25,"c3":0.75},{"time":1.1667}]},"L_forearm":{"rotate":[{"angle":-2.04,"curve":0.25,"c3":0.75},{"time":0.2667,"angle":-20.06,"curve":0.25,"c3":0.75},{"time":0.8,"angle":-29.41,"curve":0.436,"c3":0.694,"c4":0.43},{"time":0.8667,"angle":25.79,"curve":0.145,"c2":0.4,"c3":0.336},{"time":1,"angle":-33.21,"curve":0.25,"c3":0.935,"c4":0.38},{"time":1.1,"angle":20.58,"curve":0.25,"c3":0.75},{"time":1.5333,"angle":-2.91,"curve":0.25,"c3":0.75},{"time":1.7667,"angle":-2.04}]},"R_hand":{"rotate":[{"angle":-1.67,"curve":0.25,"c3":0.75},{"time":0.3,"angle":-19.79,"curve":0.25,"c3":0.75},{"time":0.8333,"angle":6.26,"curve":0.25,"c3":0.159},{"time":0.9333,"angle":-19.41,"curve":0.25,"c3":0.92,"c4":0.37},{"time":1.1,"angle":47.76,"curve":0.25,"c3":0.75},{"time":1.5667,"angle":20.61,"curve":0.25,"c3":0.75},{"time":1.7667,"angle":-1.67}]},"R_forearm":{"rotate":[{"angle":-1.21,"curve":0.25,"c3":0.75},{"time":0.2667,"angle":-15.83,"curve":0.25,"c3":0.75},{"time":0.8,"angle":-36.72,"curve":0.436,"c3":0.694,"c4":0.43},{"time":0.8667,"angle":15.71,"curve":0.145,"c2":0.4,"c3":0.336},{"time":1,"angle":-45.31,"curve":0.25,"c3":0.935,"c4":0.38},{"time":1.1,"angle":8.48,"curve":0.25,"c3":0.75},{"time":1.5333,"angle":-0.99,"curve":0.25,"c3":0.75},{"time":1.7667,"angle":-1.21}]},"body3":{"rotate":[{"curve":0.25,"c3":0.167},{"time":0.7,"angle":9.32,"curve":0.25,"c3":0.155,"c4":0.99},{"time":1.0333,"angle":-3.04,"curve":0.25,"c3":0.75},{"time":1.1,"angle":23.9,"curve":0.25,"c3":0.155,"c4":0.99},{"time":1.1667,"angle":19.93,"curve":"stepped"},{"time":1.2667,"angle":19.93,"curve":0.25,"c3":0.75},{"time":1.7667}],"translate":[{"curve":0.25,"c3":0.167},{"time":0.6667,"y":-38.74,"curve":0.25,"c3":0.155,"c4":0.99},{"time":1,"y":323.09,"curve":0.25,"c3":0.75},{"time":1.0667,"y":-118.16,"curve":0.25,"c3":0.75},{"time":1.1333,"y":-64.1,"curve":"stepped"},{"time":1.2333,"y":-64.1,"curve":0.25,"c3":0.75},{"time":1.7667}]},"L_leg":{"rotate":[{}]},"body6":{"rotate":[{"angle":-0.54}]},"body5":{"rotate":[{"angle":-3.88}]},"move_body":{"translate":[{"time":1.0333,"curve":0.25,"c3":0.75},{"time":1.1333,"x":-22.22,"curve":"stepped"},{"time":1.2333,"x":-22.22,"curve":0.25,"c3":0.75},{"time":1.7667}]},"R_leg":{"rotate":[{"angle":0.96}]},"skirt2":{"rotate":[{"angle":4.32,"curve":0.25,"c3":0.15},{"time":0.6667,"angle":3.21,"curve":0.25,"c3":0.75},{"time":0.8,"angle":-11.12,"curve":0.25,"c3":0.75},{"time":0.9667,"angle":22.39,"curve":0.25,"c3":0.75},{"time":1.0667,"angle":52.55,"curve":0.25,"c3":0.75},{"time":1.2,"angle":-5.91},{"time":1.7667,"angle":4.32}]},"R_foot":{"rotate":[{"time":0.7,"curve":0.25,"c3":0.75},{"time":0.7667,"angle":69.9,"curve":0.25,"c3":0.75},{"time":0.9667,"angle":-17.95,"curve":0.238,"c2":0.15,"c3":0.935,"c4":0.21},{"time":1.0333}],"translate":[{"time":0.7,"curve":0.25,"c3":0.75},{"time":0.7333,"x":-16.16,"y":32.06,"curve":0.274,"c3":0.264},{"time":0.9667,"x":-37.55,"y":362.08,"curve":0.238,"c2":0.15,"c3":0.935,"c4":0.21},{"time":1.0333}]},"L_foot":{"rotate":[{"time":0.7,"curve":0.25,"c3":0.75},{"time":0.7667,"angle":69.9,"curve":0.25,"c3":0.75},{"time":0.9667,"angle":-17.95,"curve":0.238,"c2":0.15,"c3":0.935,"c4":0.21},{"time":1.0333}],"translate":[{"time":0.7,"curve":0.25,"c3":0.75},{"time":0.7333,"x":-16.16,"y":32.06,"curve":0.274,"c3":0.264},{"time":0.9667,"x":-37.55,"y":362.08,"curve":0.238,"c2":0.15,"c3":0.935,"c4":0.21},{"time":1.0333}]},"R_arm":{"rotate":[{"angle":0.16,"curve":0.25,"c3":0.75},{"time":0.2333,"angle":6.15,"curve":0.25,"c3":0.75},{"time":0.7667,"angle":61.35,"curve":0.459,"c3":0.668,"c4":0.45},{"time":0.9,"angle":-16.65,"curve":0.139,"c2":0.44,"c3":0.355},{"time":1.0333,"angle":-162.97,"curve":0.25,"c3":0.75},{"time":1.0667,"angle":-60.58,"curve":0.25,"c3":0.935,"c4":0.37},{"time":1.1,"angle":-53.19,"curve":0.25,"c3":0.75},{"time":1.5,"angle":-21.37,"curve":0.25,"c3":0.75},{"time":1.7667,"angle":0.16}],"scale":[{"time":0.9,"curve":0.25,"c3":0.75},{"time":0.9667,"x":2.058,"curve":0.25,"c3":0.947,"c4":0.39},{"time":1.0667}]},"dot":{"translate":[{"x":-2.21,"y":1.67,"curve":0.25,"c3":0.75},{"time":0.2667,"x":3.92,"y":-5.18,"curve":0.25,"c3":0.167,"c4":0.99},{"time":0.8,"x":11,"y":9.61,"curve":0.25,"c3":0.75},{"time":1.1333,"x":0.39,"y":6.08,"curve":0.25,"c3":0.75},{"time":1.2,"x":16.68,"y":9.49,"curve":0.25,"c3":0.75},{"time":1.2667,"x":0.39,"y":6.08,"curve":0.25,"c3":0.75},{"time":1.5333,"x":-2.72,"y":9.17,"curve":0.25,"c3":0.75},{"time":1.7667,"x":-2.21,"y":1.67}]},"L_hand":{"rotate":[{"angle":-1.67,"curve":0.25,"c3":0.75},{"time":0.3,"angle":-41.07,"curve":0.25,"c3":0.75},{"time":0.8333,"angle":19.63,"curve":0.25,"c3":0.159},{"time":0.9333,"angle":-30.07,"curve":0.25,"c3":0.92,"c4":0.37},{"time":1.1,"angle":37.1,"curve":0.25,"c3":0.75},{"time":1.5667,"angle":9.95,"curve":0.25,"c3":0.75},{"time":1.7667,"angle":-1.67}]},"R_leg2":{"rotate":[{"angle":-9.73}]},"fx1/1":{"translate":[{"time":1.1,"x":-635.33,"y":-36.37}],"scale":[{"time":1.1,"x":1.671,"y":2.219}]},"fx2/s1":{"translate":[{"time":1.0333,"x":-588.74}],"scale":[{"time":1.0333,"x":2}]},"fx2/s2":{"rotate":[{"time":1.0333,"angle":-0.54}],"translate":[{"time":1.0333,"x":-23.32},{"time":1.1333,"x":-627.9}],"scale":[{"time":1.0333,"x":-2}]},"eye":{"rotate":[{"time":0.2333,"curve":0.25,"c3":0.75},{"time":0.4,"angle":5.42,"curve":"stepped"},{"time":1.5,"angle":5.42,"curve":0.25,"c3":0.75},{"time":1.6667}],"translate":[{"time":0.2333,"curve":0.25,"c3":0.75},{"time":0.4,"x":-1.25,"y":6.48,"curve":"stepped"},{"time":1.5,"x":-1.25,"y":6.48,"curve":0.25,"c3":0.75},{"time":1.6667}],"scale":[{},{"time":0.2333,"x":1.179,"curve":0.25,"c3":0.75},{"time":0.4,"x":-1,"curve":"stepped"},{"time":1.5,"x":-1,"curve":0.25,"c3":0.75},{"time":1.6667}]},"box_attack":{"translate":[{"time":1.1,"x":365.02,"y":68.29}],"scale":[{"time":1.1,"x":9.402,"y":1.9}]}},"events":[{"time":1.7333,"name":"SkillComplete"}]},"skill2-1":{"slots":{"angry":{"attachment":[{"time":0.8333,"name":null}]},"weapon":{"attachment":[{"time":0.8333,"name":null}]}},"bones":{"body6":{"rotate":[{"angle":-0.54,"curve":0.25,"c3":0.75},{"time":0.9333,"angle":-32.81}]},"R_leg":{"rotate":[{"angle":0.96,"curve":0.25,"c3":0.75},{"time":0.9333,"angle":33.09}]},"head":{"rotate":[{"angle":-2.2,"curve":0.25,"c3":0.15},{"time":0.8,"angle":-29.61,"curve":0.25,"c3":0.75},{"time":0.8667,"angle":-38.17},{"time":0.9333,"angle":-35.88}]},"dot":{"translate":[{"x":-2.21,"y":1.67,"curve":0.25,"c3":0.162},{"time":0.8,"x":4.64,"y":4.82,"curve":0.25,"c3":0.155},{"time":0.8667,"x":-1.35,"y":16.24}]},"R_leg2":{"rotate":[{"angle":-9.73,"curve":0.25,"c3":0.75},{"time":0.9333,"angle":-4.2}]},"L_leg":{"rotate":[{"curve":0.25,"c3":0.75},{"time":0.9333,"angle":21.35}]},"body8":{"rotate":[{"angle":36.54,"curve":0.25,"c3":0.75},{"time":0.9333,"angle":22.72}]},"body7":{"rotate":[{"curve":0.25,"c3":0.75},{"time":0.9333,"angle":-23.53}]},"skirt2":{"rotate":[{"angle":4.32,"curve":0.25,"c3":0.15},{"time":0.6667,"angle":-7.96,"curve":0.25,"c3":0.171},{"time":0.8333,"angle":18.52}]},"body5":{"rotate":[{"angle":-3.88}]},"move_body":{"translate":[{"curve":0.25,"c3":0.15},{"time":0.6667,"x":30.87,"curve":0.25,"c3":0.161},{"time":0.7333,"x":-37.42,"curve":0.25,"c3":0.75},{"time":0.8,"x":7.47}]},"body3":{"rotate":[{"curve":0.25,"c3":0.15},{"time":0.7,"angle":-9.15,"curve":0.25,"c3":0.158},{"time":0.7667,"angle":13.4},{"time":0.9333,"angle":13.51}],"translate":[{"curve":0.25,"c3":0.15},{"time":0.6667,"y":-0.18,"curve":0.25,"c3":0.158},{"time":0.7333,"y":-20.1}]},"L_arm":{"rotate":[{"angle":0.16,"curve":0.456,"c3":0.697,"c4":0.43},{"time":0.1667,"angle":-71,"curve":0.134,"c2":0.41,"c3":0.32},{"time":0.8,"angle":118.78,"curve":0.25,"c3":0.171},{"time":0.8667,"angle":-167.87}],"translate":[{"curve":0.25,"c3":0.173},{"time":0.7667,"x":-16.02,"y":5,"curve":0.25,"c3":0.171},{"time":0.8333,"x":-4.39,"y":119.42}],"scale":[{"time":0.8,"curve":0.25,"c3":0.75},{"time":0.8333,"x":1.573,"curve":0.25,"c3":0.75},{"time":0.8667}]},"L_forearm":{"rotate":[{"angle":-2.04,"curve":0.246,"c3":0.75},{"time":0.2333,"angle":13.36,"curve":0.247,"c3":0.727,"c4":0.9},{"time":0.8,"angle":-73.05,"curve":0.35,"c2":0.65,"c3":0.684},{"time":0.8333,"angle":19.33,"curve":0.25,"c3":0.75},{"time":0.8667,"angle":19.27},{"time":0.9333,"angle":18.91}]},"L_hand":{"rotate":[{"angle":-1.67,"curve":0.25,"c3":0.75},{"time":0.3,"angle":44.16,"curve":0.25,"c3":0.75},{"time":0.8,"angle":-20.18,"curve":0.25,"c3":0.75},{"time":0.8333,"angle":39.12,"curve":0.25,"c3":0.146},{"time":0.8667,"angle":54.75}]},"R_arm":{"rotate":[{"angle":0.16,"curve":0.25,"c3":0.144,"c4":0.99},{"time":0.8,"angle":-34.28,"curve":0.25,"c3":0.171},{"time":0.8667,"angle":59}],"translate":[{"time":0.7667,"curve":0.25,"c3":0.171},{"time":0.8333,"x":0.45,"y":-92.41}]},"R_forearm":{"rotate":[{"angle":-1.21,"curve":0.246,"c3":0.144,"c4":0.99},{"time":0.8333,"angle":-1.25,"curve":0.25,"c3":0.171},{"time":0.9,"angle":5.51},{"time":0.9333,"angle":5.23}]},"R_hand":{"rotate":[{"angle":-1.67,"curve":0.25,"c3":0.144,"c4":0.99},{"time":0.8667,"angle":-9.11,"curve":0.25,"c3":0.171},{"time":0.9333,"angle":26.17}]},"skirt":{"rotate":[{"angle":-0.61,"curve":0.25,"c3":0.15},{"time":0.6667,"angle":5.06,"curve":0.25,"c3":0.158,"c4":0.99},{"time":0.8333,"angle":-20.52}]},"body4":{"rotate":[{"angle":0.67,"curve":0.25,"c3":0.15},{"time":0.7333,"angle":-22.29,"curve":0.25,"c3":0.154},{"time":0.8,"angle":27.02},{"time":0.9333,"angle":27.27}],"translate":[{"x":-0.59,"y":-0.02}]},"eye":{"rotate":[{"time":0.2333,"curve":0.25,"c3":0.75},{"time":0.4,"angle":5.42}],"translate":[{"time":0.2333,"curve":0.25,"c3":0.75},{"time":0.4,"x":-1.25,"y":6.48}],"scale":[{},{"time":0.2333,"x":1.179,"curve":0.25,"c3":0.75},{"time":0.4,"x":-1}]}},"deform":{"default":{"body":{"body":[{"time":0.7,"curve":0.25,"c3":0.158},{"time":0.7667,"offset":4,"vertices":[0.25696,-5.0979,1.01356,42.42285,15.37827,39.5503,-6.94097,106.45507,-6.94097,106.45507,-2.88983,13.54059,-3.23143,16.21311,3.59201,16.13699,-3.38416,11.0328,1.35997,11.45972,3.86255,7.29892,6.48109,5.11714,6.25454,11.25396,10.26651,7.76909,-2.34064,17.44399,4.9035,16.90331,-6.57462,34.52744,7.93037,34.24146,29.6709,102.47181,29.6709,102.47181,14.29263,62.92151,15.37827,39.5503,0,0,0,0,0,0,0,0,0.01016,-3.67637,-1.24054,-3.46074,0.15979,-6.64537,-2.10939,-6.30374,-7.94242,117.37801,32.44327,113.0844,-1.06058,119.79263,-0.47855,41.25444,13.57774,38.95886,-0.81715,45.93824,-9.28561,120.16632,32.12836,116.16332,-7.43731,110.33837,1.01356,42.42285,15.37827,39.5503,-6.94097,106.45507,29.6709,102.47181,-6.94097,106.45507,29.6709,102.47181,-4.70055,45.4419,11.03122,44.33241,-6.59936,114.5896,32.75818,110.00544,-8.17312,113.00706,30.74013,109.05233,-2.64959,36.6422,9.96774,35.3597,-9.49001,106.32662,27.23013,103.21777,-6.94097,106.45507,29.6709,102.47181]}]}}}},"skill2-2":{"slots":{"angry":{"attachment":[{"name":null}]},"weapon":{"attachment":[{"name":null}]},"smile":{"attachment":[{"name":null}]}},"bones":{"body6":{"rotate":[{"angle":-32.81}]},"R_leg":{"rotate":[{"angle":33.09}]},"head":{"rotate":[{"angle":-35.88,"curve":0.363,"c2":0.44,"c3":0.755},{"time":0.2,"angle":-38.17,"curve":0.25,"c3":0.75},{"time":0.5333,"angle":-34.54,"curve":0.258,"c3":0.619,"c4":0.45},{"time":0.6667,"angle":-35.88}]},"dot":{"translate":[{"x":-1.35,"y":16.24}]},"R_leg2":{"rotate":[{"angle":-4.2}]},"L_leg":{"rotate":[{"angle":21.35}]},"body8":{"rotate":[{"angle":22.72}]},"body7":{"rotate":[{"angle":-23.53}]},"skirt2":{"rotate":[{"angle":18.52,"curve":0.25,"c3":0.75},{"time":0.3333,"angle":22.93,"curve":0.25,"c3":0.75},{"time":0.6667,"angle":18.52}]},"body5":{"rotate":[{"angle":-3.88}]},"move_body":{"translate":[{"x":7.47}]},"body3":{"rotate":[{"angle":13.51,"curve":0.375,"c2":0.62,"c3":0.716},{"time":0.0667,"angle":13.4,"curve":0.25,"c3":0.75},{"time":0.4,"angle":14.27,"curve":0.243,"c3":0.68,"c4":0.71},{"time":0.6667,"angle":13.51}],"translate":[{"y":-20.1,"curve":0.25,"c3":0.75},{"time":0.3333,"y":-23.07,"curve":0.25,"c3":0.75},{"time":0.6667,"y":-20.1}]},"L_arm":{"rotate":[{"angle":-167.87,"curve":0.25,"c3":0.75},{"time":0.3333,"angle":-165.46,"curve":0.25,"c3":0.75},{"time":0.6667,"angle":-167.87}],"translate":[{"x":-4.39,"y":119.42}]},"L_forearm":{"rotate":[{"angle":18.91,"curve":0.375,"c2":0.62,"c3":0.716},{"time":0.0667,"angle":19.27,"curve":0.25,"c3":0.75},{"time":0.4,"angle":16.53,"curve":0.243,"c3":0.68,"c4":0.71},{"time":0.6667,"angle":18.91}]},"L_hand":{"rotate":[{"angle":54.75,"curve":0.25,"c3":0.75},{"time":0.3333,"angle":48.65,"curve":0.25,"c3":0.75},{"time":0.6667,"angle":54.75}]},"R_arm":{"rotate":[{"angle":59,"curve":0.25,"c3":0.75},{"time":0.3333,"angle":61.48,"curve":0.25,"c3":0.75},{"time":0.6667,"angle":59}],"translate":[{"x":0.45,"y":-92.41}]},"R_forearm":{"rotate":[{"angle":5.23,"curve":0.375,"c2":0.62,"c3":0.716},{"time":0.0667,"angle":5.51,"curve":0.25,"c3":0.75},{"time":0.4,"angle":3.38,"curve":0.243,"c3":0.68,"c4":0.71},{"time":0.6667,"angle":5.23}]},"R_hand":{"rotate":[{"angle":26.17,"curve":0.381,"c2":0.55,"c3":0.742},{"time":0.1333,"angle":24.76,"curve":0.25,"c3":0.75},{"time":0.4667,"angle":28.59,"curve":0.245,"c3":0.637,"c4":0.56},{"time":0.6667,"angle":26.17}]},"skirt":{"rotate":[{"angle":-20.52,"curve":0.25,"c3":0.75},{"time":0.3333,"angle":-24.05,"curve":0.25,"c3":0.75},{"time":0.6667,"angle":-20.52}]},"body4":{"rotate":[{"angle":27.27,"curve":0.381,"c2":0.55,"c3":0.742},{"time":0.1333,"angle":27.02,"curve":0.25,"c3":0.75},{"time":0.4667,"angle":27.7,"curve":0.245,"c3":0.637,"c4":0.56},{"time":0.6667,"angle":27.27}],"translate":[{"x":-0.59,"y":-0.02}]},"eye":{"translate":[{"x":16,"y":20.54}],"scale":[{"y":0.511}]}},"deform":{"default":{"body":{"body":[{"offset":4,"vertices":[0.25696,-5.0979,1.01356,42.42285,15.37827,39.5503,-6.94097,106.45507,-6.94097,106.45507,-2.88983,13.54059,-3.23143,16.21311,3.59201,16.13699,-3.38416,11.0328,1.35997,11.45972,3.86255,7.29892,6.48109,5.11714,6.25454,11.25396,10.26651,7.76909,-2.34064,17.44399,4.9035,16.90331,-6.57462,34.52744,7.93037,34.24146,29.6709,102.47181,29.6709,102.47181,14.29263,62.92151,15.37827,39.5503,0,0,0,0,0,0,0,0,0.01016,-3.67637,-1.24054,-3.46074,0.15979,-6.64537,-2.10939,-6.30374,-7.94242,117.37801,32.44327,113.0844,-1.06058,119.79263,-0.47855,41.25444,13.57774,38.95886,-0.81715,45.93824,-9.28561,120.16632,32.12836,116.16332,-7.43731,110.33837,1.01356,42.42285,15.37827,39.5503,-6.94097,106.45507,29.6709,102.47181,-6.94097,106.45507,29.6709,102.47181,-4.70055,45.4419,11.03122,44.33241,-6.59936,114.5896,32.75818,110.00544,-8.17312,113.00706,30.74013,109.05233,-2.64959,36.6422,9.96774,35.3597,-9.49001,106.32662,27.23013,103.21777,-6.94097,106.45507,29.6709,102.47181]}]}}}},"skill2-3":{"bones":{"body6":{"rotate":[{"angle":-32.81,"curve":0.25,"c3":0.75},{"time":0.6667,"angle":-0.54}]},"R_leg":{"rotate":[{"angle":33.09,"curve":0.25,"c3":0.75},{"time":0.6667,"angle":0.96}]},"head":{"rotate":[{"angle":-35.88,"curve":0.25,"c3":0.175},{"time":0.2,"angle":0.45,"curve":0.25,"c3":0.75},{"time":0.3667,"angle":-6.11,"curve":0.25,"c3":0.75},{"time":0.6667,"angle":-2.2}]},"dot":{"translate":[{"x":-1.35,"y":16.24,"curve":0.25,"c3":0.163,"c4":1.01},{"time":0.2,"x":-1.54,"y":-25.24,"curve":0.25,"c3":0.75},{"time":0.3667,"x":0.68,"y":8.64,"curve":0.25,"c3":0.75},{"time":0.6667,"x":-2.21,"y":1.67}]},"R_leg2":{"rotate":[{"angle":-4.2,"curve":0.25,"c3":0.75},{"time":0.6667,"angle":-9.73}]},"L_leg":{"rotate":[{"angle":21.35,"curve":0.25,"c3":0.75},{"time":0.6667}]},"body8":{"rotate":[{"angle":22.72,"curve":0.25,"c3":0.75},{"time":0.6667,"angle":36.54}]},"body7":{"rotate":[{"angle":-23.53,"curve":0.25,"c3":0.75},{"time":0.6667}]},"skirt2":{"rotate":[{"angle":18.52,"curve":0.25,"c3":0.155},{"time":0.2,"angle":-5.14,"curve":0.25,"c3":0.75},{"time":0.3667,"angle":2.8,"curve":0.25,"c3":0.75},{"time":0.6667,"angle":4.32}]},"body5":{"rotate":[{"angle":-3.88,"curve":0.25,"c3":0.155},{"time":0.2,"angle":13.3,"curve":0.25,"c3":0.75},{"time":0.3667,"angle":-17.55,"curve":0.25,"c3":0.75},{"time":0.6667,"angle":-3.88}]},"move_body":{"translate":[{"x":7.47,"curve":0.25,"c3":0.175},{"time":0.1,"x":37.76,"curve":0.25,"c3":0.75},{"time":0.2667}]},"body3":{"rotate":[{"angle":13.51,"curve":0.25,"c3":0.175},{"time":0.1333,"angle":-1.03,"curve":0.25,"c3":0.75},{"time":0.3,"angle":7.38,"curve":0.25,"c3":0.167},{"time":0.6667}],"translate":[{"y":-20.1,"curve":"stepped"},{"time":0.2667,"y":-20.1,"curve":0.25,"c3":0.75},{"time":0.6667}]},"L_arm":{"rotate":[{"angle":-167.87,"curve":0.25,"c3":0.175},{"time":0.1,"angle":-92.41,"curve":0.375,"c2":0.5,"c3":0.75},{"time":0.2,"angle":19.43,"curve":0.25,"c3":0.75},{"time":0.3667,"angle":13.73,"curve":0.25,"c3":0.75},{"time":0.6667,"angle":0.16}],"translate":[{"x":-4.39,"y":119.42,"curve":0.25,"c3":0.175},{"time":0.2}]},"L_forearm":{"rotate":[{"angle":18.91,"curve":0.44,"c3":0.593,"c4":0.5},{"time":0.1,"angle":-11.49,"curve":0.161,"c2":0.5,"c3":0.423},{"time":0.2,"angle":-116.72,"curve":0.25,"c3":0.75},{"time":0.3667,"angle":-105.11,"curve":0.25,"c3":0.75},{"time":0.6667,"angle":-2.04}]},"L_hand":{"rotate":[{"angle":54.75,"curve":0.25,"c3":0.175},{"time":0.2333,"angle":42.62,"curve":0.25,"c3":0.75},{"time":0.4,"angle":46.95,"curve":0.25,"c3":0.75},{"time":0.6667,"angle":-1.67}]},"R_arm":{"rotate":[{"angle":59,"curve":0.25,"c3":0.155},{"time":0.2,"angle":-15.74,"curve":0.25,"c3":0.75},{"time":0.3667,"angle":-12.32,"curve":0.25,"c3":0.75},{"time":0.6667,"angle":0.16}],"translate":[{"x":0.45,"y":-92.41,"curve":0.25,"c3":0.155},{"time":0.2}]},"R_forearm":{"rotate":[{"angle":5.23,"curve":0.25,"c3":0.155},{"time":0.2333,"angle":-22.86,"curve":0.25,"c3":0.75},{"time":0.4,"angle":-16.72,"curve":0.25,"c3":0.75},{"time":0.6667,"angle":-1.21}]},"R_hand":{"rotate":[{"angle":26.17,"curve":0.25,"c3":0.155},{"time":0.2667,"angle":-3.91,"curve":0.25,"c3":0.75},{"time":0.4333,"angle":-0.5,"curve":0.25,"c3":0.75},{"time":0.6667,"angle":-1.67}]},"skirt":{"rotate":[{"angle":-20.52,"curve":0.25,"c3":0.155},{"time":0.2,"angle":-7.79,"curve":0.25,"c3":0.75},{"time":0.3667,"angle":-17.44,"curve":0.25,"c3":0.75},{"time":0.6667,"angle":-0.61}]},"body4":{"rotate":[{"angle":27.27,"curve":0.25,"c3":0.175},{"time":0.1667,"angle":-8.57,"curve":0.25,"c3":0.75},{"time":0.3333,"angle":0.67}],"translate":[{"x":-0.59,"y":-0.02}]},"eye":{"translate":[{"x":16,"y":20.54,"curve":0.25,"c3":0.163},{"time":0.2}],"scale":[{"y":0.511,"curve":0.25,"c3":0.163},{"time":0.2}]}},"deform":{"default":{"body":{"body":[{"offset":4,"vertices":[0.25696,-5.0979,1.01356,42.42285,15.37827,39.5503,-6.94097,106.45507,-6.94097,106.45507,-2.88983,13.54059,-3.23143,16.21311,3.59201,16.13699,-3.38416,11.0328,1.35997,11.45972,3.86255,7.29892,6.48109,5.11714,6.25454,11.25396,10.26651,7.76909,-2.34064,17.44399,4.9035,16.90331,-6.57462,34.52744,7.93037,34.24146,29.6709,102.47181,29.6709,102.47181,14.29263,62.92151,15.37827,39.5503,0,0,0,0,0,0,0,0,0.01016,-3.67637,-1.24054,-3.46074,0.15979,-6.64537,-2.10939,-6.30374,-7.94242,117.37801,32.44327,113.0844,-1.06058,119.79263,-0.47855,41.25444,13.57774,38.95886,-0.81715,45.93824,-9.28561,120.16632,32.12836,116.16332,-7.43731,110.33837,1.01356,42.42285,15.37827,39.5503,-6.94097,106.45507,29.6709,102.47181,-6.94097,106.45507,29.6709,102.47181,-4.70055,45.4419,11.03122,44.33241,-6.59936,114.5896,32.75818,110.00544,-8.17312,113.00706,30.74013,109.05233,-2.64959,36.6422,9.96774,35.3597,-9.49001,106.32662,27.23013,103.21777,-6.94097,106.45507,29.6709,102.47181],"curve":0.25,"c3":0.175},{"time":0.1333}]}}},"events":[{"time":0.6333,"name":"SkillComplete"}]},"skill2-demo":{"slots":{"angry":{"attachment":[{"time":0.8333,"name":null}]},"weapon":{"attachment":[{"time":0.8333,"name":null},{"time":2.2667,"name":"weapon"}]},"smile":{"attachment":[{"time":0.8333,"name":null},{"time":2.2667,"name":"smile"}]}},"bones":{"body6":{"rotate":[{"angle":-0.54,"curve":0.25,"c3":0.75},{"time":0.9333,"angle":-32.81,"curve":"stepped"},{"time":2.2667,"angle":-32.81,"curve":0.25,"c3":0.75},{"time":2.9333,"angle":-0.54}]},"R_leg":{"rotate":[{"angle":0.96,"curve":0.25,"c3":0.75},{"time":0.9333,"angle":33.09,"curve":"stepped"},{"time":2.2667,"angle":33.09,"curve":0.25,"c3":0.75},{"time":2.9333,"angle":0.96}]},"head":{"rotate":[{"angle":-2.2,"curve":0.25,"c3":0.15},{"time":0.8,"angle":-29.61,"curve":0.25,"c3":0.75},{"time":0.8667,"angle":-38.17},{"time":0.9333,"angle":-35.88,"curve":0.363,"c2":0.44,"c3":0.755},{"time":1.1333,"angle":-38.17,"curve":0.25,"c3":0.75},{"time":1.4667,"angle":-34.54,"curve":0.258,"c3":0.619,"c4":0.45},{"time":1.6,"angle":-35.88,"curve":0.363,"c2":0.44,"c3":0.755},{"time":1.8,"angle":-38.17,"curve":0.25,"c3":0.75},{"time":2.1333,"angle":-34.54,"curve":0.258,"c3":0.619,"c4":0.45},{"time":2.2667,"angle":-35.88,"curve":0.25,"c3":0.175},{"time":2.4667,"angle":0.45,"curve":0.25,"c3":0.75},{"time":2.6333,"angle":-6.11,"curve":0.25,"c3":0.75},{"time":2.9333,"angle":-2.2}]},"dot":{"translate":[{"x":-2.21,"y":1.67,"curve":0.25,"c3":0.162},{"time":0.8,"x":16.21,"y":-0.07,"curve":0.25,"c3":0.155},{"time":0.8667,"x":-1.35,"y":16.24,"curve":"stepped"},{"time":2.2667,"x":-1.35,"y":16.24,"curve":0.25,"c3":0.163},{"time":2.4667,"x":-1.69,"y":-19.41,"curve":0.25,"c3":0.75},{"time":2.6333,"x":0.17,"y":0.32},{"time":2.9333,"x":-2.21,"y":1.67}]},"R_leg2":{"rotate":[{"angle":-9.73,"curve":0.25,"c3":0.75},{"time":0.9333,"angle":-4.2,"curve":"stepped"},{"time":2.2667,"angle":-4.2,"curve":0.25,"c3":0.75},{"time":2.9333,"angle":-9.73}]},"L_leg":{"rotate":[{"curve":0.25,"c3":0.75},{"time":0.9333,"angle":21.35,"curve":"stepped"},{"time":2.2667,"angle":21.35,"curve":0.25,"c3":0.75},{"time":2.9333}]},"body8":{"rotate":[{"angle":36.54,"curve":0.25,"c3":0.75},{"time":0.9333,"angle":22.72,"curve":"stepped"},{"time":2.2667,"angle":22.72,"curve":0.25,"c3":0.75},{"time":2.9333,"angle":36.54}]},"body7":{"rotate":[{"curve":0.25,"c3":0.75},{"time":0.9333,"angle":-23.53,"curve":"stepped"},{"time":2.2667,"angle":-23.53,"curve":0.25,"c3":0.75},{"time":2.9333}]},"skirt2":{"rotate":[{"angle":4.32,"curve":0.25,"c3":0.15},{"time":0.6667,"angle":-7.96,"curve":0.25,"c3":0.171},{"time":0.8333,"angle":18.52,"curve":"stepped"},{"time":0.9333,"angle":18.52,"curve":0.25,"c3":0.75},{"time":1.2667,"angle":22.93,"curve":0.25,"c3":0.75},{"time":1.6,"angle":18.52,"curve":0.25,"c3":0.75},{"time":1.9333,"angle":22.93,"curve":0.25,"c3":0.75},{"time":2.2667,"angle":18.52,"curve":0.25,"c3":0.155},{"time":2.4667,"angle":-5.14,"curve":0.25,"c3":0.75},{"time":2.6333,"angle":2.8,"curve":0.25,"c3":0.75},{"time":2.9333,"angle":4.32}]},"body5":{"rotate":[{"angle":-3.88,"curve":"stepped"},{"time":2.2667,"angle":-3.88,"curve":0.25,"c3":0.155},{"time":2.4667,"angle":13.3,"curve":0.25,"c3":0.75},{"time":2.6333,"angle":-17.55,"curve":0.25,"c3":0.75},{"time":2.9333,"angle":-3.88}]},"move_body":{"translate":[{"curve":0.25,"c3":0.15},{"time":0.6667,"x":30.87,"curve":0.25,"c3":0.161},{"time":0.7333,"x":-37.42,"curve":0.25,"c3":0.75},{"time":0.8,"x":7.47,"curve":"stepped"},{"time":2.2667,"x":7.47,"curve":0.25,"c3":0.175},{"time":2.3667,"x":37.76,"curve":0.25,"c3":0.75},{"time":2.5333}]},"body3":{"rotate":[{"curve":0.25,"c3":0.15},{"time":0.7,"angle":-9.15,"curve":0.25,"c3":0.158},{"time":0.7667,"angle":13.4},{"time":0.9333,"angle":13.51,"curve":0.375,"c2":0.62,"c3":0.716},{"time":1,"angle":13.4,"curve":0.25,"c3":0.75},{"time":1.3333,"angle":14.27,"curve":0.243,"c3":0.68,"c4":0.71},{"time":1.6,"angle":13.51,"curve":0.375,"c2":0.62,"c3":0.716},{"time":1.6667,"angle":13.4,"curve":0.25,"c3":0.75},{"time":2,"angle":14.27,"curve":0.243,"c3":0.68,"c4":0.71},{"time":2.2667,"angle":13.51,"curve":0.25,"c3":0.175},{"time":2.4,"angle":-1.03,"curve":0.25,"c3":0.75},{"time":2.5667,"angle":7.38,"curve":0.25,"c3":0.167},{"time":2.9333}],"translate":[{"curve":0.25,"c3":0.15},{"time":0.6667,"y":-0.18,"curve":0.25,"c3":0.158},{"time":0.7333,"y":-20.1,"curve":"stepped"},{"time":0.9333,"y":-20.1,"curve":0.25,"c3":0.75},{"time":1.2667,"y":-23.07,"curve":0.25,"c3":0.75},{"time":1.6,"y":-20.1,"curve":0.25,"c3":0.75},{"time":1.9333,"y":-23.07,"curve":0.25,"c3":0.75},{"time":2.2667,"y":-20.1,"curve":"stepped"},{"time":2.5333,"y":-20.1,"curve":0.25,"c3":0.75},{"time":2.9333}]},"L_arm":{"rotate":[{"angle":0.16,"curve":0.456,"c3":0.697,"c4":0.43},{"time":0.1667,"angle":-71,"curve":0.134,"c2":0.41,"c3":0.32},{"time":0.8,"angle":118.78,"curve":0.25,"c3":0.171},{"time":0.8667,"angle":-167.87,"curve":"stepped"},{"time":0.9333,"angle":-167.87,"curve":0.25,"c3":0.75},{"time":1.2667,"angle":-165.46,"curve":0.25,"c3":0.75},{"time":1.6,"angle":-167.87,"curve":0.25,"c3":0.75},{"time":1.9333,"angle":-165.46,"curve":0.25,"c3":0.75},{"time":2.2667,"angle":-167.87,"curve":0.25,"c3":0.175},{"time":2.3667,"angle":-92.41,"curve":0.375,"c2":0.5,"c3":0.75},{"time":2.4667,"angle":19.43,"curve":0.25,"c3":0.75},{"time":2.6333,"angle":13.73,"curve":0.25,"c3":0.75},{"time":2.9333,"angle":0.16}],"translate":[{"curve":0.25,"c3":0.173},{"time":0.7667,"x":-16.02,"y":5,"curve":0.25,"c3":0.171},{"time":0.8333,"x":-4.39,"y":119.42,"curve":"stepped"},{"time":2.2667,"x":-4.39,"y":119.42,"curve":0.25,"c3":0.175},{"time":2.4667}],"scale":[{"time":0.8,"curve":0.25,"c3":0.75},{"time":0.8333,"x":1.573,"curve":0.25,"c3":0.75},{"time":0.8667}]},"L_forearm":{"rotate":[{"angle":-2.04,"curve":0.246,"c3":0.75},{"time":0.2333,"angle":13.36,"curve":0.247,"c3":0.727,"c4":0.9},{"time":0.8,"angle":-73.05,"curve":0.35,"c2":0.65,"c3":0.684},{"time":0.8333,"angle":19.33,"curve":0.25,"c3":0.75},{"time":0.8667,"angle":19.27},{"time":0.9333,"angle":18.91,"curve":0.375,"c2":0.62,"c3":0.716},{"time":1,"angle":19.27,"curve":0.25,"c3":0.75},{"time":1.3333,"angle":16.53,"curve":0.243,"c3":0.68,"c4":0.71},{"time":1.6,"angle":18.91,"curve":0.375,"c2":0.62,"c3":0.716},{"time":1.6667,"angle":19.27,"curve":0.25,"c3":0.75},{"time":2,"angle":16.53,"curve":0.243,"c3":0.68,"c4":0.71},{"time":2.2667,"angle":18.91,"curve":0.44,"c3":0.593,"c4":0.5},{"time":2.3667,"angle":-11.49,"curve":0.161,"c2":0.5,"c3":0.423},{"time":2.4667,"angle":-116.72,"curve":0.25,"c3":0.75},{"time":2.6333,"angle":-105.11,"curve":0.25,"c3":0.75},{"time":2.9333,"angle":-2.04}]},"L_hand":{"rotate":[{"angle":-1.67,"curve":0.25,"c3":0.75},{"time":0.3,"angle":44.16,"curve":0.25,"c3":0.75},{"time":0.8,"angle":-20.18,"curve":0.25,"c3":0.75},{"time":0.8333,"angle":39.12,"curve":0.25,"c3":0.146},{"time":0.8667,"angle":54.75,"curve":"stepped"},{"time":0.9333,"angle":54.75,"curve":0.25,"c3":0.75},{"time":1.2667,"angle":48.65,"curve":0.25,"c3":0.75},{"time":1.6,"angle":54.75,"curve":0.25,"c3":0.75},{"time":1.9333,"angle":48.65,"curve":0.25,"c3":0.75},{"time":2.2667,"angle":54.75,"curve":0.25,"c3":0.175},{"time":2.5,"angle":42.62,"curve":0.25,"c3":0.75},{"time":2.6667,"angle":46.95,"curve":0.25,"c3":0.75},{"time":2.9333,"angle":-1.67}]},"R_arm":{"rotate":[{"angle":0.16,"curve":0.25,"c3":0.144,"c4":0.99},{"time":0.8,"angle":-34.28,"curve":0.25,"c3":0.171},{"time":0.8667,"angle":59,"curve":"stepped"},{"time":0.9333,"angle":59,"curve":0.25,"c3":0.75},{"time":1.2667,"angle":61.48,"curve":0.25,"c3":0.75},{"time":1.6,"angle":59,"curve":0.25,"c3":0.75},{"time":1.9333,"angle":61.48,"curve":0.25,"c3":0.75},{"time":2.2667,"angle":59,"curve":0.25,"c3":0.155},{"time":2.4667,"angle":-15.74,"curve":0.25,"c3":0.75},{"time":2.6333,"angle":-12.32,"curve":0.25,"c3":0.75},{"time":2.9333,"angle":0.16}],"translate":[{"time":0.7667,"curve":0.25,"c3":0.171},{"time":0.8333,"x":0.45,"y":-92.41,"curve":"stepped"},{"time":2.2667,"x":0.45,"y":-92.41,"curve":0.25,"c3":0.155},{"time":2.4667}]},"R_forearm":{"rotate":[{"angle":-1.21,"curve":0.246,"c3":0.144,"c4":0.99},{"time":0.8333,"angle":-1.25,"curve":0.25,"c3":0.171},{"time":0.9,"angle":5.51},{"time":0.9333,"angle":5.23,"curve":0.375,"c2":0.62,"c3":0.716},{"time":1,"angle":5.51,"curve":0.25,"c3":0.75},{"time":1.3333,"angle":3.38,"curve":0.243,"c3":0.68,"c4":0.71},{"time":1.6,"angle":5.23,"curve":0.375,"c2":0.62,"c3":0.716},{"time":1.6667,"angle":5.51,"curve":0.25,"c3":0.75},{"time":2,"angle":3.38,"curve":0.243,"c3":0.68,"c4":0.71},{"time":2.2667,"angle":5.23,"curve":0.25,"c3":0.155},{"time":2.5,"angle":-22.86,"curve":0.25,"c3":0.75},{"time":2.6667,"angle":-16.72,"curve":0.25,"c3":0.75},{"time":2.9333,"angle":-1.21}]},"R_hand":{"rotate":[{"angle":-1.67,"curve":0.25,"c3":0.144,"c4":0.99},{"time":0.8667,"angle":-9.11,"curve":0.25,"c3":0.171},{"time":0.9333,"angle":26.17,"curve":0.381,"c2":0.55,"c3":0.742},{"time":1.0667,"angle":24.76,"curve":0.25,"c3":0.75},{"time":1.4,"angle":28.59,"curve":0.245,"c3":0.637,"c4":0.56},{"time":1.6,"angle":26.17,"curve":0.381,"c2":0.55,"c3":0.742},{"time":1.7333,"angle":24.76,"curve":0.25,"c3":0.75},{"time":2.0667,"angle":28.59,"curve":0.245,"c3":0.637,"c4":0.56},{"time":2.2667,"angle":26.17,"curve":0.25,"c3":0.155},{"time":2.5333,"angle":-3.91,"curve":0.25,"c3":0.75},{"time":2.7,"angle":-0.5,"curve":0.25,"c3":0.75},{"time":2.9333,"angle":-1.67}]},"skirt":{"rotate":[{"angle":-0.61,"curve":0.25,"c3":0.15},{"time":0.6667,"angle":5.06,"curve":0.25,"c3":0.158,"c4":0.99},{"time":0.8333,"angle":-20.52,"curve":"stepped"},{"time":0.9333,"angle":-20.52,"curve":0.25,"c3":0.75},{"time":1.2667,"angle":-24.05,"curve":0.25,"c3":0.75},{"time":1.6,"angle":-20.52,"curve":0.25,"c3":0.75},{"time":1.9333,"angle":-24.05,"curve":0.25,"c3":0.75},{"time":2.2667,"angle":-20.52,"curve":0.25,"c3":0.155},{"time":2.4667,"angle":-7.79,"curve":0.25,"c3":0.75},{"time":2.6333,"angle":-17.44,"curve":0.25,"c3":0.75},{"time":2.9333,"angle":-0.61}]},"body4":{"rotate":[{"angle":0.67,"curve":0.25,"c3":0.15},{"time":0.7333,"angle":-22.29,"curve":0.25,"c3":0.154},{"time":0.8,"angle":27.02},{"time":0.9333,"angle":27.27,"curve":0.381,"c2":0.55,"c3":0.742},{"time":1.0667,"angle":27.02,"curve":0.25,"c3":0.75},{"time":1.4,"angle":27.7,"curve":0.245,"c3":0.637,"c4":0.56},{"time":1.6,"angle":27.27,"curve":0.381,"c2":0.55,"c3":0.742},{"time":1.7333,"angle":27.02,"curve":0.25,"c3":0.75},{"time":2.0667,"angle":27.7,"curve":0.245,"c3":0.637,"c4":0.56},{"time":2.2667,"angle":27.27,"curve":0.25,"c3":0.175},{"time":2.4333,"angle":-8.57,"curve":0.25,"c3":0.75},{"time":2.6,"angle":0.67}],"translate":[{"x":-0.59,"y":-0.02}]},"eye":{"translate":[{"time":0.7667,"curve":0.25,"c3":0.152,"c4":0.99},{"time":0.8333,"x":16,"y":20.54,"curve":"stepped"},{"time":2.2667,"x":16,"y":20.54,"curve":0.25,"c3":0.163},{"time":2.4667}],"scale":[{"time":0.7667,"curve":0.25,"c3":0.152,"c4":0.99},{"time":0.8333,"y":0.511,"curve":"stepped"},{"time":2.2667,"y":0.511,"curve":0.25,"c3":0.163},{"time":2.4667}]}},"deform":{"default":{"body":{"body":[{"time":0.7,"curve":0.25,"c3":0.158},{"time":0.7667,"offset":4,"vertices":[0.25696,-5.0979,1.01356,42.42285,15.37827,39.5503,-6.94097,106.45507,-6.94097,106.45507,-2.88983,13.54059,-3.23143,16.21311,3.59201,16.13699,-3.38416,11.0328,1.35997,11.45972,3.86255,7.29892,6.48109,5.11714,6.25454,11.25396,10.26651,7.76909,-2.34064,17.44399,4.9035,16.90331,-6.57462,34.52744,7.93037,34.24146,29.6709,102.47181,29.6709,102.47181,14.29263,62.92151,15.37827,39.5503,0,0,0,0,0,0,0,0,0.01016,-3.67637,-1.24054,-3.46074,0.15979,-6.64537,-2.10939,-6.30374,-7.94242,117.37801,32.44327,113.0844,-1.06058,119.79263,-0.47855,41.25444,13.57774,38.95886,-0.81715,45.93824,-9.28561,120.16632,32.12836,116.16332,-7.43731,110.33837,1.01356,42.42285,15.37827,39.5503,-6.94097,106.45507,29.6709,102.47181,-6.94097,106.45507,29.6709,102.47181,-4.70055,45.4419,11.03122,44.33241,-6.59936,114.5896,32.75818,110.00544,-8.17312,113.00706,30.74013,109.05233,-2.64959,36.6422,9.96774,35.3597,-9.49001,106.32662,27.23013,103.21777,-6.94097,106.45507,29.6709,102.47181],"curve":"stepped"},{"time":2.2667,"offset":4,"vertices":[0.25696,-5.0979,1.01356,42.42285,15.37827,39.5503,-6.94097,106.45507,-6.94097,106.45507,-2.88983,13.54059,-3.23143,16.21311,3.59201,16.13699,-3.38416,11.0328,1.35997,11.45972,3.86255,7.29892,6.48109,5.11714,6.25454,11.25396,10.26651,7.76909,-2.34064,17.44399,4.9035,16.90331,-6.57462,34.52744,7.93037,34.24146,29.6709,102.47181,29.6709,102.47181,14.29263,62.92151,15.37827,39.5503,0,0,0,0,0,0,0,0,0.01016,-3.67637,-1.24054,-3.46074,0.15979,-6.64537,-2.10939,-6.30374,-7.94242,117.37801,32.44327,113.0844,-1.06058,119.79263,-0.47855,41.25444,13.57774,38.95886,-0.81715,45.93824,-9.28561,120.16632,32.12836,116.16332,-7.43731,110.33837,1.01356,42.42285,15.37827,39.5503,-6.94097,106.45507,29.6709,102.47181,-6.94097,106.45507,29.6709,102.47181,-4.70055,45.4419,11.03122,44.33241,-6.59936,114.5896,32.75818,110.00544,-8.17312,113.00706,30.74013,109.05233,-2.64959,36.6422,9.96774,35.3597,-9.49001,106.32662,27.23013,103.21777,-6.94097,106.45507,29.6709,102.47181],"curve":0.25,"c3":0.175},{"time":2.4}]}}},"events":[{"time":2.9,"name":"SkillComplete"}]}}}